[
  {
    "count": 43064,
    "borough": "Bronx",
    "timeBucket": "Issued Pandemic"
  },
  {
    "count": 8693,
    "borough": "Bronx",
    "timeBucket": "Issued Prepandemic"
  },
  {
    "count": 26494,
    "borough": "Brooklyn",
    "timeBucket": "Issued Pandemic"
  },
  {
    "count": 8136,
    "borough": "Brooklyn",
    "timeBucket": "Issued Prepandemic"
  },
  {
    "count": 21073,
    "borough": "Manhattan",
    "timeBucket": "Issued Pandemic"
  },
  {
    "count": 9353,
    "borough": "Manhattan",
    "timeBucket": "Issued Prepandemic"
  },
  {
    "count": 18826,
    "borough": "Queens",
    "timeBucket": "Issued Pandemic"
  },
  {
    "count": 6819,
    "borough": "Queens",
    "timeBucket": "Issued Prepandemic"
  },
  {
    "count": 2150,
    "borough": "Staten Island",
    "timeBucket": "Issued Pandemic"
  },
  {
    "count": 467,
    "borough": "Staten Island",
    "timeBucket": "Issued Prepandemic"
  }
]