[
  {
    "borough": "Queens",
    "region": "NYC",
    "two_months_ago": "1785",
    "three_months_ago": "1537",
    "num_increase": "248",
    "percent_increase": "16"
  },
  {
    "borough": "Outside NYC",
    "region": "Outside NYC",
    "two_months_ago": "4337",
    "three_months_ago": "4154",
    "num_increase": "183",
    "percent_increase": "4"
  },
  {
    "borough": "Manhattan",
    "region": "NYC",
    "two_months_ago": "2002",
    "three_months_ago": "2024",
    "num_increase": "-22",
    "percent_increase": "-1"
  },
  {
    "borough": "Bronx",
    "region": "NYC",
    "two_months_ago": "3851",
    "three_months_ago": "3970",
    "num_increase": "-119",
    "percent_increase": "-3"
  },
  {
    "borough": "Staten Island",
    "region": "NYC",
    "two_months_ago": "245",
    "three_months_ago": "262",
    "num_increase": "-17",
    "percent_increase": "-6"
  },
  {
    "borough": "Brooklyn",
    "region": "NYC",
    "two_months_ago": "1580",
    "three_months_ago": "2185",
    "num_increase": "-605",
    "percent_increase": "-28"
  }
]