[
  {
    "day": "2015-12-28T05:00:00.000Z",
    "active_cases": 0
  },
  {
    "day": "2016-01-04T05:00:00.000Z",
    "active_cases": 127
  },
  {
    "day": "2016-01-11T05:00:00.000Z",
    "active_cases": 269
  },
  {
    "day": "2016-01-18T05:00:00.000Z",
    "active_cases": 350
  },
  {
    "day": "2016-01-25T05:00:00.000Z",
    "active_cases": 454
  },
  {
    "day": "2016-02-01T05:00:00.000Z",
    "active_cases": 587
  },
  {
    "day": "2016-02-08T05:00:00.000Z",
    "active_cases": 680
  },
  {
    "day": "2016-02-15T05:00:00.000Z",
    "active_cases": 851
  },
  {
    "day": "2016-02-22T05:00:00.000Z",
    "active_cases": 1005
  },
  {
    "day": "2016-02-29T05:00:00.000Z",
    "active_cases": 1126
  },
  {
    "day": "2016-03-07T05:00:00.000Z",
    "active_cases": 1233
  },
  {
    "day": "2016-03-14T04:00:00.000Z",
    "active_cases": 1339
  },
  {
    "day": "2016-03-21T04:00:00.000Z",
    "active_cases": 1462
  },
  {
    "day": "2016-03-28T04:00:00.000Z",
    "active_cases": 1550
  },
  {
    "day": "2016-04-04T04:00:00.000Z",
    "active_cases": 1644
  },
  {
    "day": "2016-04-11T04:00:00.000Z",
    "active_cases": 1750
  },
  {
    "day": "2016-04-18T04:00:00.000Z",
    "active_cases": 1837
  },
  {
    "day": "2016-04-25T04:00:00.000Z",
    "active_cases": 1947
  },
  {
    "day": "2016-05-02T04:00:00.000Z",
    "active_cases": 2040
  },
  {
    "day": "2016-05-09T04:00:00.000Z",
    "active_cases": 2151
  },
  {
    "day": "2016-05-16T04:00:00.000Z",
    "active_cases": 2232
  },
  {
    "day": "2016-05-23T04:00:00.000Z",
    "active_cases": 2331
  },
  {
    "day": "2016-05-30T04:00:00.000Z",
    "active_cases": 2405
  },
  {
    "day": "2016-06-06T04:00:00.000Z",
    "active_cases": 2512
  },
  {
    "day": "2016-06-13T04:00:00.000Z",
    "active_cases": 2634
  },
  {
    "day": "2016-06-20T04:00:00.000Z",
    "active_cases": 2736
  },
  {
    "day": "2016-06-27T04:00:00.000Z",
    "active_cases": 2842
  },
  {
    "day": "2016-07-04T04:00:00.000Z",
    "active_cases": 2924
  },
  {
    "day": "2016-07-11T04:00:00.000Z",
    "active_cases": 3063
  },
  {
    "day": "2016-07-18T04:00:00.000Z",
    "active_cases": 3200
  },
  {
    "day": "2016-07-25T04:00:00.000Z",
    "active_cases": 3292
  },
  {
    "day": "2016-08-01T04:00:00.000Z",
    "active_cases": 3386
  },
  {
    "day": "2016-08-08T04:00:00.000Z",
    "active_cases": 3522
  },
  {
    "day": "2016-08-15T04:00:00.000Z",
    "active_cases": 3627
  },
  {
    "day": "2016-08-22T04:00:00.000Z",
    "active_cases": 3725
  },
  {
    "day": "2016-08-29T04:00:00.000Z",
    "active_cases": 3808
  },
  {
    "day": "2016-09-05T04:00:00.000Z",
    "active_cases": 3893
  },
  {
    "day": "2016-09-12T04:00:00.000Z",
    "active_cases": 4016
  },
  {
    "day": "2016-09-19T04:00:00.000Z",
    "active_cases": 4153
  },
  {
    "day": "2016-09-26T04:00:00.000Z",
    "active_cases": 4269
  },
  {
    "day": "2016-10-03T04:00:00.000Z",
    "active_cases": 4385
  },
  {
    "day": "2016-10-10T04:00:00.000Z",
    "active_cases": 4490
  },
  {
    "day": "2016-10-17T04:00:00.000Z",
    "active_cases": 4623
  },
  {
    "day": "2016-10-24T04:00:00.000Z",
    "active_cases": 4698
  },
  {
    "day": "2016-10-31T04:00:00.000Z",
    "active_cases": 4811
  },
  {
    "day": "2016-11-07T05:00:00.000Z",
    "active_cases": 4927
  },
  {
    "day": "2016-11-14T05:00:00.000Z",
    "active_cases": 5068
  },
  {
    "day": "2016-11-21T05:00:00.000Z",
    "active_cases": 5184
  },
  {
    "day": "2016-11-28T05:00:00.000Z",
    "active_cases": 5302
  },
  {
    "day": "2016-12-05T05:00:00.000Z",
    "active_cases": 5441
  },
  {
    "day": "2016-12-12T05:00:00.000Z",
    "active_cases": 5561
  },
  {
    "day": "2016-12-19T05:00:00.000Z",
    "active_cases": 5669
  },
  {
    "day": "2016-12-26T05:00:00.000Z",
    "active_cases": 5752
  },
  {
    "day": "2017-01-02T05:00:00.000Z",
    "active_cases": 5820
  },
  {
    "day": "2017-01-09T05:00:00.000Z",
    "active_cases": 5939
  },
  {
    "day": "2017-01-16T05:00:00.000Z",
    "active_cases": 6042
  },
  {
    "day": "2017-01-23T05:00:00.000Z",
    "active_cases": 6167
  },
  {
    "day": "2017-01-30T05:00:00.000Z",
    "active_cases": 6306
  },
  {
    "day": "2017-02-06T05:00:00.000Z",
    "active_cases": 6445
  },
  {
    "day": "2017-02-13T05:00:00.000Z",
    "active_cases": 6557
  },
  {
    "day": "2017-02-20T05:00:00.000Z",
    "active_cases": 6658
  },
  {
    "day": "2017-02-27T05:00:00.000Z",
    "active_cases": 6756
  },
  {
    "day": "2017-03-06T05:00:00.000Z",
    "active_cases": 6865
  },
  {
    "day": "2017-03-13T04:00:00.000Z",
    "active_cases": 6954
  },
  {
    "day": "2017-03-20T04:00:00.000Z",
    "active_cases": 7063
  },
  {
    "day": "2017-03-27T04:00:00.000Z",
    "active_cases": 7158
  },
  {
    "day": "2017-04-03T04:00:00.000Z",
    "active_cases": 7282
  },
  {
    "day": "2017-04-10T04:00:00.000Z",
    "active_cases": 7388
  },
  {
    "day": "2017-04-17T04:00:00.000Z",
    "active_cases": 7461
  },
  {
    "day": "2017-04-24T04:00:00.000Z",
    "active_cases": 7555
  },
  {
    "day": "2017-05-01T04:00:00.000Z",
    "active_cases": 7644
  },
  {
    "day": "2017-05-08T04:00:00.000Z",
    "active_cases": 7752
  },
  {
    "day": "2017-05-15T04:00:00.000Z",
    "active_cases": 7835
  },
  {
    "day": "2017-05-22T04:00:00.000Z",
    "active_cases": 7927
  },
  {
    "day": "2017-05-29T04:00:00.000Z",
    "active_cases": 7993
  },
  {
    "day": "2017-06-05T04:00:00.000Z",
    "active_cases": 8104
  },
  {
    "day": "2017-06-12T04:00:00.000Z",
    "active_cases": 8204
  },
  {
    "day": "2017-06-19T04:00:00.000Z",
    "active_cases": 8295
  },
  {
    "day": "2017-06-26T04:00:00.000Z",
    "active_cases": 8395
  },
  {
    "day": "2017-07-03T04:00:00.000Z",
    "active_cases": 8442
  },
  {
    "day": "2017-07-10T04:00:00.000Z",
    "active_cases": 8587
  },
  {
    "day": "2017-07-17T04:00:00.000Z",
    "active_cases": 8693
  },
  {
    "day": "2017-07-24T04:00:00.000Z",
    "active_cases": 8786
  },
  {
    "day": "2017-07-31T04:00:00.000Z",
    "active_cases": 8877
  },
  {
    "day": "2017-08-07T04:00:00.000Z",
    "active_cases": 9022
  },
  {
    "day": "2017-08-14T04:00:00.000Z",
    "active_cases": 9108
  },
  {
    "day": "2017-08-21T04:00:00.000Z",
    "active_cases": 9202
  },
  {
    "day": "2017-08-28T04:00:00.000Z",
    "active_cases": 9288
  },
  {
    "day": "2017-09-04T04:00:00.000Z",
    "active_cases": 9374
  },
  {
    "day": "2017-09-11T04:00:00.000Z",
    "active_cases": 9480
  },
  {
    "day": "2017-09-18T04:00:00.000Z",
    "active_cases": 9586
  },
  {
    "day": "2017-09-25T04:00:00.000Z",
    "active_cases": 9679
  },
  {
    "day": "2017-10-02T04:00:00.000Z",
    "active_cases": 9777
  },
  {
    "day": "2017-10-09T04:00:00.000Z",
    "active_cases": 9875
  },
  {
    "day": "2017-10-16T04:00:00.000Z",
    "active_cases": 10023
  },
  {
    "day": "2017-10-23T04:00:00.000Z",
    "active_cases": 10120
  },
  {
    "day": "2017-10-30T04:00:00.000Z",
    "active_cases": 10226
  },
  {
    "day": "2017-11-06T05:00:00.000Z",
    "active_cases": 10337
  },
  {
    "day": "2017-11-13T05:00:00.000Z",
    "active_cases": 10459
  },
  {
    "day": "2017-11-20T05:00:00.000Z",
    "active_cases": 10519
  },
  {
    "day": "2017-11-27T05:00:00.000Z",
    "active_cases": 10596
  },
  {
    "day": "2017-12-04T05:00:00.000Z",
    "active_cases": 10717
  },
  {
    "day": "2017-12-11T05:00:00.000Z",
    "active_cases": 10829
  },
  {
    "day": "2017-12-18T05:00:00.000Z",
    "active_cases": 10968
  },
  {
    "day": "2017-12-25T05:00:00.000Z",
    "active_cases": 11037
  },
  {
    "day": "2018-01-01T05:00:00.000Z",
    "active_cases": 11741
  },
  {
    "day": "2018-01-08T05:00:00.000Z",
    "active_cases": 13329
  },
  {
    "day": "2018-01-15T05:00:00.000Z",
    "active_cases": 14530
  },
  {
    "day": "2018-01-22T05:00:00.000Z",
    "active_cases": 15988
  },
  {
    "day": "2018-01-29T05:00:00.000Z",
    "active_cases": 17141
  },
  {
    "day": "2018-02-05T05:00:00.000Z",
    "active_cases": 18777
  },
  {
    "day": "2018-02-12T05:00:00.000Z",
    "active_cases": 20348
  },
  {
    "day": "2018-02-19T05:00:00.000Z",
    "active_cases": 21575
  },
  {
    "day": "2018-02-26T05:00:00.000Z",
    "active_cases": 22775
  },
  {
    "day": "2018-03-05T05:00:00.000Z",
    "active_cases": 24083
  },
  {
    "day": "2018-03-12T04:00:00.000Z",
    "active_cases": 25556
  },
  {
    "day": "2018-03-19T04:00:00.000Z",
    "active_cases": 26636
  },
  {
    "day": "2018-03-26T04:00:00.000Z",
    "active_cases": 27830
  },
  {
    "day": "2018-04-02T04:00:00.000Z",
    "active_cases": 29040
  },
  {
    "day": "2018-04-09T04:00:00.000Z",
    "active_cases": 30256
  },
  {
    "day": "2018-04-16T04:00:00.000Z",
    "active_cases": 31397
  },
  {
    "day": "2018-04-23T04:00:00.000Z",
    "active_cases": 32355
  },
  {
    "day": "2018-04-30T04:00:00.000Z",
    "active_cases": 33283
  },
  {
    "day": "2018-05-07T04:00:00.000Z",
    "active_cases": 34652
  },
  {
    "day": "2018-05-14T04:00:00.000Z",
    "active_cases": 35645
  },
  {
    "day": "2018-05-21T04:00:00.000Z",
    "active_cases": 36536
  },
  {
    "day": "2018-05-28T04:00:00.000Z",
    "active_cases": 37256
  },
  {
    "day": "2018-06-04T04:00:00.000Z",
    "active_cases": 38440
  },
  {
    "day": "2018-06-11T04:00:00.000Z",
    "active_cases": 39703
  },
  {
    "day": "2018-06-18T04:00:00.000Z",
    "active_cases": 40752
  },
  {
    "day": "2018-06-25T04:00:00.000Z",
    "active_cases": 41737
  },
  {
    "day": "2018-07-02T04:00:00.000Z",
    "active_cases": 42456
  },
  {
    "day": "2018-07-09T04:00:00.000Z",
    "active_cases": 43766
  },
  {
    "day": "2018-07-16T04:00:00.000Z",
    "active_cases": 44970
  },
  {
    "day": "2018-07-23T04:00:00.000Z",
    "active_cases": 46203
  },
  {
    "day": "2018-07-30T04:00:00.000Z",
    "active_cases": 47233
  },
  {
    "day": "2018-08-06T04:00:00.000Z",
    "active_cases": 48468
  },
  {
    "day": "2018-08-13T04:00:00.000Z",
    "active_cases": 49915
  },
  {
    "day": "2018-08-20T04:00:00.000Z",
    "active_cases": 51154
  },
  {
    "day": "2018-08-27T04:00:00.000Z",
    "active_cases": 52070
  },
  {
    "day": "2018-09-03T04:00:00.000Z",
    "active_cases": 52963
  },
  {
    "day": "2018-09-10T04:00:00.000Z",
    "active_cases": 54260
  },
  {
    "day": "2018-09-17T04:00:00.000Z",
    "active_cases": 55438
  },
  {
    "day": "2018-09-24T04:00:00.000Z",
    "active_cases": 56296
  },
  {
    "day": "2018-10-01T04:00:00.000Z",
    "active_cases": 57485
  },
  {
    "day": "2018-10-08T04:00:00.000Z",
    "active_cases": 58727
  },
  {
    "day": "2018-10-15T04:00:00.000Z",
    "active_cases": 60258
  },
  {
    "day": "2018-10-22T04:00:00.000Z",
    "active_cases": 61301
  },
  {
    "day": "2018-10-29T04:00:00.000Z",
    "active_cases": 62614
  },
  {
    "day": "2018-11-05T05:00:00.000Z",
    "active_cases": 64020
  },
  {
    "day": "2018-11-12T05:00:00.000Z",
    "active_cases": 65442
  },
  {
    "day": "2018-11-19T05:00:00.000Z",
    "active_cases": 66229
  },
  {
    "day": "2018-11-26T05:00:00.000Z",
    "active_cases": 67237
  },
  {
    "day": "2018-12-03T05:00:00.000Z",
    "active_cases": 68538
  },
  {
    "day": "2018-12-10T05:00:00.000Z",
    "active_cases": 69905
  },
  {
    "day": "2018-12-17T05:00:00.000Z",
    "active_cases": 71164
  },
  {
    "day": "2018-12-24T05:00:00.000Z",
    "active_cases": 71974
  },
  {
    "day": "2018-12-31T05:00:00.000Z",
    "active_cases": 72891
  },
  {
    "day": "2019-01-07T05:00:00.000Z",
    "active_cases": 74535
  },
  {
    "day": "2019-01-14T05:00:00.000Z",
    "active_cases": 75848
  },
  {
    "day": "2019-01-21T05:00:00.000Z",
    "active_cases": 76953
  },
  {
    "day": "2019-01-28T05:00:00.000Z",
    "active_cases": 78182
  },
  {
    "day": "2019-02-04T05:00:00.000Z",
    "active_cases": 79504
  },
  {
    "day": "2019-02-11T05:00:00.000Z",
    "active_cases": 81014
  },
  {
    "day": "2019-02-18T05:00:00.000Z",
    "active_cases": 82182
  },
  {
    "day": "2019-02-25T05:00:00.000Z",
    "active_cases": 83584
  },
  {
    "day": "2019-03-04T05:00:00.000Z",
    "active_cases": 84874
  },
  {
    "day": "2019-03-11T04:00:00.000Z",
    "active_cases": 86166
  },
  {
    "day": "2019-03-18T04:00:00.000Z",
    "active_cases": 87401
  },
  {
    "day": "2019-03-25T04:00:00.000Z",
    "active_cases": 88302
  },
  {
    "day": "2019-04-01T04:00:00.000Z",
    "active_cases": 89578
  },
  {
    "day": "2019-04-08T04:00:00.000Z",
    "active_cases": 90710
  },
  {
    "day": "2019-04-15T04:00:00.000Z",
    "active_cases": 91914
  },
  {
    "day": "2019-04-22T04:00:00.000Z",
    "active_cases": 92903
  },
  {
    "day": "2019-04-29T04:00:00.000Z",
    "active_cases": 93903
  },
  {
    "day": "2019-05-06T04:00:00.000Z",
    "active_cases": 95212
  },
  {
    "day": "2019-05-13T04:00:00.000Z",
    "active_cases": 96397
  },
  {
    "day": "2019-05-20T04:00:00.000Z",
    "active_cases": 97485
  },
  {
    "day": "2019-05-27T04:00:00.000Z",
    "active_cases": 98176
  },
  {
    "day": "2019-06-03T04:00:00.000Z",
    "active_cases": 99285
  },
  {
    "day": "2019-06-10T04:00:00.000Z",
    "active_cases": 100554
  },
  {
    "day": "2019-06-17T04:00:00.000Z",
    "active_cases": 101528
  },
  {
    "day": "2019-06-24T04:00:00.000Z",
    "active_cases": 101908
  },
  {
    "day": "2019-07-01T04:00:00.000Z",
    "active_cases": 102261
  },
  {
    "day": "2019-07-08T04:00:00.000Z",
    "active_cases": 102621
  },
  {
    "day": "2019-07-15T04:00:00.000Z",
    "active_cases": 103097
  },
  {
    "day": "2019-07-22T04:00:00.000Z",
    "active_cases": 103469
  },
  {
    "day": "2019-07-29T04:00:00.000Z",
    "active_cases": 103940
  },
  {
    "day": "2019-08-05T04:00:00.000Z",
    "active_cases": 104599
  },
  {
    "day": "2019-08-12T04:00:00.000Z",
    "active_cases": 105805
  },
  {
    "day": "2019-08-19T04:00:00.000Z",
    "active_cases": 106798
  },
  {
    "day": "2019-08-26T04:00:00.000Z",
    "active_cases": 107587
  },
  {
    "day": "2019-09-02T04:00:00.000Z",
    "active_cases": 108321
  },
  {
    "day": "2019-09-09T04:00:00.000Z",
    "active_cases": 109356
  },
  {
    "day": "2019-09-16T04:00:00.000Z",
    "active_cases": 110327
  },
  {
    "day": "2019-09-23T04:00:00.000Z",
    "active_cases": 111470
  },
  {
    "day": "2019-09-30T04:00:00.000Z",
    "active_cases": 112252
  },
  {
    "day": "2019-10-07T04:00:00.000Z",
    "active_cases": 113132
  },
  {
    "day": "2019-10-14T04:00:00.000Z",
    "active_cases": 114053
  },
  {
    "day": "2019-10-21T04:00:00.000Z",
    "active_cases": 115122
  },
  {
    "day": "2019-10-28T04:00:00.000Z",
    "active_cases": 116179
  },
  {
    "day": "2019-11-04T05:00:00.000Z",
    "active_cases": 117234
  },
  {
    "day": "2019-11-11T05:00:00.000Z",
    "active_cases": 118162
  },
  {
    "day": "2019-11-18T05:00:00.000Z",
    "active_cases": 119470
  },
  {
    "day": "2019-11-25T05:00:00.000Z",
    "active_cases": 120199
  },
  {
    "day": "2019-12-02T05:00:00.000Z",
    "active_cases": 121297
  },
  {
    "day": "2019-12-09T05:00:00.000Z",
    "active_cases": 122920
  },
  {
    "day": "2019-12-16T05:00:00.000Z",
    "active_cases": 124271
  },
  {
    "day": "2019-12-23T05:00:00.000Z",
    "active_cases": 124916
  },
  {
    "day": "2019-12-30T05:00:00.000Z",
    "active_cases": 125750
  },
  {
    "day": "2020-01-06T05:00:00.000Z",
    "active_cases": 127095
  },
  {
    "day": "2020-01-13T05:00:00.000Z",
    "active_cases": 128633
  },
  {
    "day": "2020-01-20T05:00:00.000Z",
    "active_cases": 129996
  },
  {
    "day": "2020-01-27T05:00:00.000Z",
    "active_cases": 131237
  },
  {
    "day": "2020-02-03T05:00:00.000Z",
    "active_cases": 132898
  },
  {
    "day": "2020-02-10T05:00:00.000Z",
    "active_cases": 134433
  },
  {
    "day": "2020-02-17T05:00:00.000Z",
    "active_cases": 136151
  },
  {
    "day": "2020-02-24T05:00:00.000Z",
    "active_cases": 138014
  },
  {
    "day": "2020-03-02T05:00:00.000Z",
    "active_cases": 140322
  },
  {
    "day": "2020-03-09T04:00:00.000Z",
    "active_cases": 142492
  },
  {
    "day": "2020-03-16T04:00:00.000Z",
    "active_cases": 144313
  },
  {
    "day": "2020-03-23T04:00:00.000Z",
    "active_cases": 144314
  },
  {
    "day": "2020-04-06T04:00:00.000Z",
    "active_cases": 144314
  },
  {
    "day": "2020-04-13T04:00:00.000Z",
    "active_cases": 144315
  },
  {
    "day": "2020-04-27T04:00:00.000Z",
    "active_cases": 144315
  },
  {
    "day": "2020-05-11T04:00:00.000Z",
    "active_cases": 144318
  },
  {
    "day": "2020-05-25T04:00:00.000Z",
    "active_cases": 144318
  },
  {
    "day": "2020-06-01T04:00:00.000Z",
    "active_cases": 144319
  },
  {
    "day": "2020-06-08T04:00:00.000Z",
    "active_cases": 144320
  },
  {
    "day": "2020-06-15T04:00:00.000Z",
    "active_cases": 144321
  },
  {
    "day": "2020-06-22T04:00:00.000Z",
    "active_cases": 144323
  },
  {
    "day": "2020-06-29T04:00:00.000Z",
    "active_cases": 144327
  },
  {
    "day": "2020-07-06T04:00:00.000Z",
    "active_cases": 144359
  },
  {
    "day": "2020-07-13T04:00:00.000Z",
    "active_cases": 144438
  },
  {
    "day": "2020-07-20T04:00:00.000Z",
    "active_cases": 144586
  },
  {
    "day": "2020-07-27T04:00:00.000Z",
    "active_cases": 145277
  },
  {
    "day": "2020-08-03T04:00:00.000Z",
    "active_cases": 145555
  },
  {
    "day": "2020-08-10T04:00:00.000Z",
    "active_cases": 146087
  },
  {
    "day": "2020-08-17T04:00:00.000Z",
    "active_cases": 146889
  },
  {
    "day": "2020-08-24T04:00:00.000Z",
    "active_cases": 148061
  },
  {
    "day": "2020-08-31T04:00:00.000Z",
    "active_cases": 149048
  },
  {
    "day": "2020-09-07T04:00:00.000Z",
    "active_cases": 149774
  },
  {
    "day": "2020-09-14T04:00:00.000Z",
    "active_cases": 150715
  },
  {
    "day": "2020-09-21T04:00:00.000Z",
    "active_cases": 151698
  },
  {
    "day": "2020-09-28T04:00:00.000Z",
    "active_cases": 152464
  },
  {
    "day": "2020-10-05T04:00:00.000Z",
    "active_cases": 153368
  },
  {
    "day": "2020-10-12T04:00:00.000Z",
    "active_cases": 154184
  },
  {
    "day": "2020-10-19T04:00:00.000Z",
    "active_cases": 155245
  },
  {
    "day": "2020-10-26T04:00:00.000Z",
    "active_cases": 156192
  },
  {
    "day": "2020-11-02T05:00:00.000Z",
    "active_cases": 157222
  },
  {
    "day": "2020-11-09T05:00:00.000Z",
    "active_cases": 158161
  },
  {
    "day": "2020-11-16T05:00:00.000Z",
    "active_cases": 159232
  },
  {
    "day": "2020-11-23T05:00:00.000Z",
    "active_cases": 159988
  },
  {
    "day": "2020-11-30T05:00:00.000Z",
    "active_cases": 160891
  },
  {
    "day": "2020-12-07T05:00:00.000Z",
    "active_cases": 161775
  },
  {
    "day": "2020-12-14T05:00:00.000Z",
    "active_cases": 162787
  },
  {
    "day": "2020-12-21T05:00:00.000Z",
    "active_cases": 163866
  },
  {
    "day": "2020-12-28T05:00:00.000Z",
    "active_cases": 164309
  },
  {
    "day": "2021-01-04T05:00:00.000Z",
    "active_cases": 164334
  },
  {
    "day": "2021-01-11T05:00:00.000Z",
    "active_cases": 164405
  },
  {
    "day": "2021-01-18T05:00:00.000Z",
    "active_cases": 164461
  },
  {
    "day": "2021-01-25T05:00:00.000Z",
    "active_cases": 164522
  },
  {
    "day": "2021-02-01T05:00:00.000Z",
    "active_cases": 164597
  },
  {
    "day": "2021-02-08T05:00:00.000Z",
    "active_cases": 164769
  },
  {
    "day": "2021-02-15T05:00:00.000Z",
    "active_cases": 164927
  },
  {
    "day": "2021-02-22T05:00:00.000Z",
    "active_cases": 165235
  },
  {
    "day": "2021-03-01T05:00:00.000Z",
    "active_cases": 165619
  },
  {
    "day": "2021-03-08T05:00:00.000Z",
    "active_cases": 165957
  },
  {
    "day": "2021-03-15T04:00:00.000Z",
    "active_cases": 166227
  },
  {
    "day": "2021-03-22T04:00:00.000Z",
    "active_cases": 166789
  },
  {
    "day": "2021-03-29T04:00:00.000Z",
    "active_cases": 167335
  },
  {
    "day": "2021-04-05T04:00:00.000Z",
    "active_cases": 167930
  },
  {
    "day": "2021-04-12T04:00:00.000Z",
    "active_cases": 168443
  },
  {
    "day": "2021-04-19T04:00:00.000Z",
    "active_cases": 168944
  },
  {
    "day": "2021-04-26T04:00:00.000Z",
    "active_cases": 169597
  },
  {
    "day": "2021-05-03T04:00:00.000Z",
    "active_cases": 170196
  },
  {
    "day": "2021-05-10T04:00:00.000Z",
    "active_cases": 171010
  },
  {
    "day": "2021-05-17T04:00:00.000Z",
    "active_cases": 171721
  },
  {
    "day": "2021-05-24T04:00:00.000Z",
    "active_cases": 172433
  },
  {
    "day": "2021-05-31T04:00:00.000Z",
    "active_cases": 172948
  },
  {
    "day": "2021-06-07T04:00:00.000Z",
    "active_cases": 173645
  },
  {
    "day": "2021-06-14T04:00:00.000Z",
    "active_cases": 174245
  },
  {
    "day": "2021-06-21T04:00:00.000Z",
    "active_cases": 174838
  },
  {
    "day": "2021-06-28T04:00:00.000Z",
    "active_cases": 175478
  },
  {
    "day": "2021-07-05T04:00:00.000Z",
    "active_cases": 175932
  },
  {
    "day": "2021-07-12T04:00:00.000Z",
    "active_cases": 176419
  },
  {
    "day": "2021-07-19T04:00:00.000Z",
    "active_cases": 177007
  },
  {
    "day": "2021-07-26T04:00:00.000Z",
    "active_cases": 177572
  },
  {
    "day": "2021-08-02T04:00:00.000Z",
    "active_cases": 178084
  },
  {
    "day": "2021-08-09T04:00:00.000Z",
    "active_cases": 178639
  },
  {
    "day": "2021-08-16T04:00:00.000Z",
    "active_cases": 179232
  },
  {
    "day": "2021-08-23T04:00:00.000Z",
    "active_cases": 179961
  },
  {
    "day": "2021-08-30T04:00:00.000Z",
    "active_cases": 180467
  },
  {
    "day": "2021-09-06T04:00:00.000Z",
    "active_cases": 180588
  },
  {
    "day": "2021-09-13T04:00:00.000Z",
    "active_cases": 180846
  },
  {
    "day": "2021-09-20T04:00:00.000Z",
    "active_cases": 181170
  },
  {
    "day": "2021-09-27T04:00:00.000Z",
    "active_cases": 181622
  },
  {
    "day": "2021-10-04T04:00:00.000Z",
    "active_cases": 182056
  },
  {
    "day": "2021-10-11T04:00:00.000Z",
    "active_cases": 182633
  },
  {
    "day": "2021-10-18T04:00:00.000Z",
    "active_cases": 183138
  },
  {
    "day": "2021-10-25T04:00:00.000Z",
    "active_cases": 183517
  },
  {
    "day": "2021-11-01T04:00:00.000Z",
    "active_cases": 184030
  },
  {
    "day": "2021-11-08T05:00:00.000Z",
    "active_cases": 184515
  },
  {
    "day": "2021-11-15T05:00:00.000Z",
    "active_cases": 185073
  },
  {
    "day": "2021-11-22T05:00:00.000Z",
    "active_cases": 185453
  },
  {
    "day": "2021-11-29T05:00:00.000Z",
    "active_cases": 185993
  },
  {
    "day": "2021-12-06T05:00:00.000Z",
    "active_cases": 186498
  },
  {
    "day": "2021-12-13T05:00:00.000Z",
    "active_cases": 186974
  },
  {
    "day": "2021-12-20T05:00:00.000Z",
    "active_cases": 187365
  },
  {
    "day": "2021-12-27T05:00:00.000Z",
    "active_cases": 187843
  },
  {
    "day": "2022-01-03T05:00:00.000Z",
    "active_cases": 188343
  },
  {
    "day": "2022-01-10T05:00:00.000Z",
    "active_cases": 189055
  },
  {
    "day": "2022-01-17T05:00:00.000Z",
    "active_cases": 189838
  },
  {
    "day": "2022-01-24T05:00:00.000Z",
    "active_cases": 190706
  },
  {
    "day": "2022-01-31T05:00:00.000Z",
    "active_cases": 191541
  },
  {
    "day": "2022-02-07T05:00:00.000Z",
    "active_cases": 192497
  },
  {
    "day": "2022-02-14T05:00:00.000Z",
    "active_cases": 193516
  },
  {
    "day": "2022-02-21T05:00:00.000Z",
    "active_cases": 194587
  },
  {
    "day": "2022-02-28T05:00:00.000Z",
    "active_cases": 195539
  },
  {
    "day": "2022-03-07T05:00:00.000Z",
    "active_cases": 196874
  },
  {
    "day": "2022-03-14T04:00:00.000Z",
    "active_cases": 198249
  },
  {
    "day": "2022-03-21T04:00:00.000Z",
    "active_cases": 199529
  },
  {
    "day": "2022-03-28T04:00:00.000Z",
    "active_cases": 200927
  },
  {
    "day": "2022-04-04T04:00:00.000Z",
    "active_cases": 202391
  },
  {
    "day": "2022-04-11T04:00:00.000Z",
    "active_cases": 203845
  },
  {
    "day": "2022-04-18T04:00:00.000Z",
    "active_cases": 205512
  },
  {
    "day": "2022-04-25T04:00:00.000Z",
    "active_cases": 206924
  },
  {
    "day": "2022-05-02T04:00:00.000Z",
    "active_cases": 208315
  },
  {
    "day": "2022-05-09T04:00:00.000Z",
    "active_cases": 209837
  },
  {
    "day": "2022-05-16T04:00:00.000Z",
    "active_cases": 211264
  },
  {
    "day": "2022-05-23T04:00:00.000Z",
    "active_cases": 212704
  },
  {
    "day": "2022-05-30T04:00:00.000Z",
    "active_cases": 213897
  },
  {
    "day": "2022-06-06T04:00:00.000Z",
    "active_cases": 215759
  },
  {
    "day": "2022-06-13T04:00:00.000Z",
    "active_cases": 217306
  },
  {
    "day": "2022-06-20T04:00:00.000Z",
    "active_cases": 218547
  },
  {
    "day": "2022-06-27T04:00:00.000Z",
    "active_cases": 220492
  },
  {
    "day": "2022-07-04T04:00:00.000Z",
    "active_cases": 222035
  },
  {
    "day": "2022-07-11T04:00:00.000Z",
    "active_cases": 223984
  },
  {
    "day": "2022-07-18T04:00:00.000Z",
    "active_cases": 226190
  },
  {
    "day": "2022-07-25T04:00:00.000Z",
    "active_cases": 227820
  },
  {
    "day": "2022-08-01T04:00:00.000Z",
    "active_cases": 229892
  },
  {
    "day": "2022-08-08T04:00:00.000Z",
    "active_cases": 231962
  },
  {
    "day": "2022-08-15T04:00:00.000Z",
    "active_cases": 233685
  },
  {
    "day": "2022-08-22T04:00:00.000Z",
    "active_cases": 235125
  },
  {
    "day": "2022-08-29T04:00:00.000Z",
    "active_cases": 237309
  },
  {
    "day": "2022-09-05T04:00:00.000Z",
    "active_cases": 239639
  },
  {
    "day": "2022-09-12T04:00:00.000Z",
    "active_cases": 242241
  },
  {
    "day": "2022-09-19T04:00:00.000Z",
    "active_cases": 244996
  },
  {
    "day": "2022-09-26T04:00:00.000Z",
    "active_cases": 247551
  },
  {
    "day": "2022-10-03T04:00:00.000Z",
    "active_cases": 250424
  },
  {
    "day": "2022-10-10T04:00:00.000Z",
    "active_cases": 253261
  },
  {
    "day": "2022-10-17T04:00:00.000Z",
    "active_cases": 256353
  },
  {
    "day": "2022-10-24T04:00:00.000Z",
    "active_cases": 259371
  },
  {
    "day": "2022-10-31T04:00:00.000Z",
    "active_cases": 263127
  },
  {
    "day": "2022-11-07T05:00:00.000Z",
    "active_cases": 265932
  },
  {
    "day": "2022-11-14T05:00:00.000Z",
    "active_cases": 268082
  },
  {
    "day": "2022-11-21T05:00:00.000Z",
    "active_cases": 269170
  },
  {
    "day": "2022-11-28T05:00:00.000Z",
    "active_cases": 269300
  }
]