[
  {
    "count": 786,
    "category": "Outside NYC.Issued Prepandemic.All.Non-Payment"
  },
  {
    "count": 284,
    "category": "Outside NYC.Issued Prepandemic.All.Holdover"
  },
  {
    "count": 631,
    "category": "NYC.Issued Pandemic.Commercial.Holdover"
  },
  {
    "count": 134373,
    "category": "NYC.Issued Prepandemic.Residential.Non-Payment"
  },
  {
    "count": 9280,
    "category": "NYC.Issued Prepandemic.Residential.Holdover"
  },
  {
    "count": 1742,
    "category": "NYC.Issued Pandemic.Commercial.Non-Payment"
  },
  {
    "count": 7390,
    "category": "Outside NYC.Issued Pandemic.All.Non-Payment"
  },
  {
    "count": 2760,
    "category": "Outside NYC.Issued Pandemic.All.Holdover"
  },
  {
    "count": 620,
    "category": "NYC.Issued Prepandemic.Commercial.Holdover"
  },
  {
    "count": 48049,
    "category": "NYC.Issued Pandemic.Residential.Non-Payment"
  },
  {
    "count": 11146,
    "category": "NYC.Issued Pandemic.Residential.Holdover"
  },
  {
    "count": 7558,
    "category": "NYC.Issued Prepandemic.Commercial.Non-Payment"
  }
]