[
  {
    "count": 1121,
    "category": "NYC.Issued Prepandemic.Commercial.Non-Payment"
  },
  {
    "count": 129,
    "category": "Outside NYC.Issued Pandemic.All.Holdover"
  },
  {
    "count": 7450,
    "category": "Outside NYC.Issued Pandemic.Residential.Non-Payment"
  },
  {
    "count": 697,
    "category": "NYC.Issued Pandemic.Commercial.Holdover"
  },
  {
    "count": 552,
    "category": "NYC.Issued Prepandemic.Commercial.Holdover"
  },
  {
    "count": 420,
    "category": "Outside NYC.Issued Pandemic.All.Non-Payment"
  },
  {
    "count": 65,
    "category": "Outside NYC.Issued Pandemic.Commercial.Holdover"
  },
  {
    "count": 6762,
    "category": "NYC.Issued Prepandemic.Residential.Holdover"
  },
  {
    "count": 376,
    "category": "Outside NYC.Issued Prepandemic.All.Non-Payment"
  },
  {
    "count": 4201,
    "category": "NYC.Issued Pandemic.Commercial.Non-Payment"
  },
  {
    "count": 160,
    "category": "Outside NYC.Issued Pandemic.Commercial.Non-Payment"
  },
  {
    "count": 24431,
    "category": "NYC.Issued Prepandemic.Residential.Non-Payment"
  },
  {
    "count": 69,
    "category": "Outside NYC.Issued Prepandemic.All.Holdover"
  },
  {
    "count": 109306,
    "category": "NYC.Issued Pandemic.Residential.Non-Payment"
  },
  {
    "count": 1924,
    "category": "Outside NYC.Issued Pandemic.Residential.Holdover"
  },
  {
    "count": 16928,
    "category": "NYC.Issued Pandemic.Residential.Holdover"
  }
]