[
  {
    "day": "2015-12-28T05:00:00.000Z",
    "active_cases": 0
  },
  {
    "day": "2016-01-04T05:00:00.000Z",
    "active_cases": 73
  },
  {
    "day": "2016-01-11T05:00:00.000Z",
    "active_cases": 161
  },
  {
    "day": "2016-01-18T05:00:00.000Z",
    "active_cases": 210
  },
  {
    "day": "2016-01-25T05:00:00.000Z",
    "active_cases": 262
  },
  {
    "day": "2016-02-01T05:00:00.000Z",
    "active_cases": 332
  },
  {
    "day": "2016-02-08T05:00:00.000Z",
    "active_cases": 379
  },
  {
    "day": "2016-02-15T05:00:00.000Z",
    "active_cases": 476
  },
  {
    "day": "2016-02-22T05:00:00.000Z",
    "active_cases": 570
  },
  {
    "day": "2016-02-29T05:00:00.000Z",
    "active_cases": 638
  },
  {
    "day": "2016-03-07T05:00:00.000Z",
    "active_cases": 681
  },
  {
    "day": "2016-03-14T04:00:00.000Z",
    "active_cases": 732
  },
  {
    "day": "2016-03-21T04:00:00.000Z",
    "active_cases": 804
  },
  {
    "day": "2016-03-28T04:00:00.000Z",
    "active_cases": 848
  },
  {
    "day": "2016-04-04T04:00:00.000Z",
    "active_cases": 898
  },
  {
    "day": "2016-04-11T04:00:00.000Z",
    "active_cases": 953
  },
  {
    "day": "2016-04-18T04:00:00.000Z",
    "active_cases": 993
  },
  {
    "day": "2016-04-25T04:00:00.000Z",
    "active_cases": 1059
  },
  {
    "day": "2016-05-02T04:00:00.000Z",
    "active_cases": 1098
  },
  {
    "day": "2016-05-09T04:00:00.000Z",
    "active_cases": 1154
  },
  {
    "day": "2016-05-16T04:00:00.000Z",
    "active_cases": 1194
  },
  {
    "day": "2016-05-23T04:00:00.000Z",
    "active_cases": 1237
  },
  {
    "day": "2016-05-30T04:00:00.000Z",
    "active_cases": 1282
  },
  {
    "day": "2016-06-06T04:00:00.000Z",
    "active_cases": 1327
  },
  {
    "day": "2016-06-13T04:00:00.000Z",
    "active_cases": 1390
  },
  {
    "day": "2016-06-20T04:00:00.000Z",
    "active_cases": 1442
  },
  {
    "day": "2016-06-27T04:00:00.000Z",
    "active_cases": 1497
  },
  {
    "day": "2016-07-04T04:00:00.000Z",
    "active_cases": 1537
  },
  {
    "day": "2016-07-11T04:00:00.000Z",
    "active_cases": 1613
  },
  {
    "day": "2016-07-18T04:00:00.000Z",
    "active_cases": 1694
  },
  {
    "day": "2016-07-25T04:00:00.000Z",
    "active_cases": 1741
  },
  {
    "day": "2016-08-01T04:00:00.000Z",
    "active_cases": 1776
  },
  {
    "day": "2016-08-08T04:00:00.000Z",
    "active_cases": 1863
  },
  {
    "day": "2016-08-15T04:00:00.000Z",
    "active_cases": 1919
  },
  {
    "day": "2016-08-22T04:00:00.000Z",
    "active_cases": 1960
  },
  {
    "day": "2016-08-29T04:00:00.000Z",
    "active_cases": 1986
  },
  {
    "day": "2016-09-05T04:00:00.000Z",
    "active_cases": 2024
  },
  {
    "day": "2016-09-12T04:00:00.000Z",
    "active_cases": 2084
  },
  {
    "day": "2016-09-19T04:00:00.000Z",
    "active_cases": 2169
  },
  {
    "day": "2016-09-26T04:00:00.000Z",
    "active_cases": 2227
  },
  {
    "day": "2016-10-03T04:00:00.000Z",
    "active_cases": 2279
  },
  {
    "day": "2016-10-10T04:00:00.000Z",
    "active_cases": 2343
  },
  {
    "day": "2016-10-17T04:00:00.000Z",
    "active_cases": 2419
  },
  {
    "day": "2016-10-24T04:00:00.000Z",
    "active_cases": 2459
  },
  {
    "day": "2016-10-31T04:00:00.000Z",
    "active_cases": 2513
  },
  {
    "day": "2016-11-07T05:00:00.000Z",
    "active_cases": 2573
  },
  {
    "day": "2016-11-14T05:00:00.000Z",
    "active_cases": 2653
  },
  {
    "day": "2016-11-21T05:00:00.000Z",
    "active_cases": 2720
  },
  {
    "day": "2016-11-28T05:00:00.000Z",
    "active_cases": 2793
  },
  {
    "day": "2016-12-05T05:00:00.000Z",
    "active_cases": 2879
  },
  {
    "day": "2016-12-12T05:00:00.000Z",
    "active_cases": 2953
  },
  {
    "day": "2016-12-19T05:00:00.000Z",
    "active_cases": 3022
  },
  {
    "day": "2016-12-26T05:00:00.000Z",
    "active_cases": 3061
  },
  {
    "day": "2017-01-02T05:00:00.000Z",
    "active_cases": 3102
  },
  {
    "day": "2017-01-09T05:00:00.000Z",
    "active_cases": 3165
  },
  {
    "day": "2017-01-16T05:00:00.000Z",
    "active_cases": 3232
  },
  {
    "day": "2017-01-23T05:00:00.000Z",
    "active_cases": 3293
  },
  {
    "day": "2017-01-30T05:00:00.000Z",
    "active_cases": 3380
  },
  {
    "day": "2017-02-06T05:00:00.000Z",
    "active_cases": 3468
  },
  {
    "day": "2017-02-13T05:00:00.000Z",
    "active_cases": 3533
  },
  {
    "day": "2017-02-20T05:00:00.000Z",
    "active_cases": 3584
  },
  {
    "day": "2017-02-27T05:00:00.000Z",
    "active_cases": 3642
  },
  {
    "day": "2017-03-06T05:00:00.000Z",
    "active_cases": 3703
  },
  {
    "day": "2017-03-13T04:00:00.000Z",
    "active_cases": 3753
  },
  {
    "day": "2017-03-20T04:00:00.000Z",
    "active_cases": 3811
  },
  {
    "day": "2017-03-27T04:00:00.000Z",
    "active_cases": 3863
  },
  {
    "day": "2017-04-03T04:00:00.000Z",
    "active_cases": 3929
  },
  {
    "day": "2017-04-10T04:00:00.000Z",
    "active_cases": 3989
  },
  {
    "day": "2017-04-17T04:00:00.000Z",
    "active_cases": 4025
  },
  {
    "day": "2017-04-24T04:00:00.000Z",
    "active_cases": 4078
  },
  {
    "day": "2017-05-01T04:00:00.000Z",
    "active_cases": 4116
  },
  {
    "day": "2017-05-08T04:00:00.000Z",
    "active_cases": 4176
  },
  {
    "day": "2017-05-15T04:00:00.000Z",
    "active_cases": 4216
  },
  {
    "day": "2017-05-22T04:00:00.000Z",
    "active_cases": 4266
  },
  {
    "day": "2017-05-29T04:00:00.000Z",
    "active_cases": 4292
  },
  {
    "day": "2017-06-05T04:00:00.000Z",
    "active_cases": 4352
  },
  {
    "day": "2017-06-12T04:00:00.000Z",
    "active_cases": 4398
  },
  {
    "day": "2017-06-19T04:00:00.000Z",
    "active_cases": 4454
  },
  {
    "day": "2017-06-26T04:00:00.000Z",
    "active_cases": 4504
  },
  {
    "day": "2017-07-03T04:00:00.000Z",
    "active_cases": 4523
  },
  {
    "day": "2017-07-10T04:00:00.000Z",
    "active_cases": 4608
  },
  {
    "day": "2017-07-17T04:00:00.000Z",
    "active_cases": 4663
  },
  {
    "day": "2017-07-24T04:00:00.000Z",
    "active_cases": 4707
  },
  {
    "day": "2017-07-31T04:00:00.000Z",
    "active_cases": 4747
  },
  {
    "day": "2017-08-07T04:00:00.000Z",
    "active_cases": 4837
  },
  {
    "day": "2017-08-14T04:00:00.000Z",
    "active_cases": 4873
  },
  {
    "day": "2017-08-21T04:00:00.000Z",
    "active_cases": 4921
  },
  {
    "day": "2017-08-28T04:00:00.000Z",
    "active_cases": 4960
  },
  {
    "day": "2017-09-04T04:00:00.000Z",
    "active_cases": 5019
  },
  {
    "day": "2017-09-11T04:00:00.000Z",
    "active_cases": 5070
  },
  {
    "day": "2017-09-18T04:00:00.000Z",
    "active_cases": 5111
  },
  {
    "day": "2017-09-25T04:00:00.000Z",
    "active_cases": 5163
  },
  {
    "day": "2017-10-02T04:00:00.000Z",
    "active_cases": 5208
  },
  {
    "day": "2017-10-09T04:00:00.000Z",
    "active_cases": 5268
  },
  {
    "day": "2017-10-16T04:00:00.000Z",
    "active_cases": 5347
  },
  {
    "day": "2017-10-23T04:00:00.000Z",
    "active_cases": 5404
  },
  {
    "day": "2017-10-30T04:00:00.000Z",
    "active_cases": 5465
  },
  {
    "day": "2017-11-06T05:00:00.000Z",
    "active_cases": 5530
  },
  {
    "day": "2017-11-13T05:00:00.000Z",
    "active_cases": 5585
  },
  {
    "day": "2017-11-20T05:00:00.000Z",
    "active_cases": 5614
  },
  {
    "day": "2017-11-27T05:00:00.000Z",
    "active_cases": 5652
  },
  {
    "day": "2017-12-04T05:00:00.000Z",
    "active_cases": 5718
  },
  {
    "day": "2017-12-11T05:00:00.000Z",
    "active_cases": 5778
  },
  {
    "day": "2017-12-18T05:00:00.000Z",
    "active_cases": 5865
  },
  {
    "day": "2017-12-25T05:00:00.000Z",
    "active_cases": 5904
  },
  {
    "day": "2018-01-01T05:00:00.000Z",
    "active_cases": 5945
  },
  {
    "day": "2018-01-08T05:00:00.000Z",
    "active_cases": 6021
  },
  {
    "day": "2018-01-15T05:00:00.000Z",
    "active_cases": 6099
  },
  {
    "day": "2018-01-22T05:00:00.000Z",
    "active_cases": 6170
  },
  {
    "day": "2018-01-29T05:00:00.000Z",
    "active_cases": 6237
  },
  {
    "day": "2018-02-05T05:00:00.000Z",
    "active_cases": 6333
  },
  {
    "day": "2018-02-12T05:00:00.000Z",
    "active_cases": 6425
  },
  {
    "day": "2018-02-19T05:00:00.000Z",
    "active_cases": 6482
  },
  {
    "day": "2018-02-26T05:00:00.000Z",
    "active_cases": 6547
  },
  {
    "day": "2018-03-05T05:00:00.000Z",
    "active_cases": 6649
  },
  {
    "day": "2018-03-12T04:00:00.000Z",
    "active_cases": 6702
  },
  {
    "day": "2018-03-19T04:00:00.000Z",
    "active_cases": 6748
  },
  {
    "day": "2018-03-26T04:00:00.000Z",
    "active_cases": 6824
  },
  {
    "day": "2018-04-02T04:00:00.000Z",
    "active_cases": 6911
  },
  {
    "day": "2018-04-09T04:00:00.000Z",
    "active_cases": 6980
  },
  {
    "day": "2018-04-16T04:00:00.000Z",
    "active_cases": 7027
  },
  {
    "day": "2018-04-23T04:00:00.000Z",
    "active_cases": 7066
  },
  {
    "day": "2018-04-30T04:00:00.000Z",
    "active_cases": 7146
  },
  {
    "day": "2018-05-07T04:00:00.000Z",
    "active_cases": 7220
  },
  {
    "day": "2018-05-14T04:00:00.000Z",
    "active_cases": 7275
  },
  {
    "day": "2018-05-21T04:00:00.000Z",
    "active_cases": 7317
  },
  {
    "day": "2018-05-28T04:00:00.000Z",
    "active_cases": 7362
  },
  {
    "day": "2018-06-04T04:00:00.000Z",
    "active_cases": 7454
  },
  {
    "day": "2018-06-11T04:00:00.000Z",
    "active_cases": 7534
  },
  {
    "day": "2018-06-18T04:00:00.000Z",
    "active_cases": 7604
  },
  {
    "day": "2018-06-25T04:00:00.000Z",
    "active_cases": 7662
  },
  {
    "day": "2018-07-02T04:00:00.000Z",
    "active_cases": 7705
  },
  {
    "day": "2018-07-09T04:00:00.000Z",
    "active_cases": 7803
  },
  {
    "day": "2018-07-16T04:00:00.000Z",
    "active_cases": 7895
  },
  {
    "day": "2018-07-23T04:00:00.000Z",
    "active_cases": 7973
  },
  {
    "day": "2018-07-30T04:00:00.000Z",
    "active_cases": 8042
  },
  {
    "day": "2018-08-06T04:00:00.000Z",
    "active_cases": 8107
  },
  {
    "day": "2018-08-13T04:00:00.000Z",
    "active_cases": 8176
  },
  {
    "day": "2018-08-20T04:00:00.000Z",
    "active_cases": 8269
  },
  {
    "day": "2018-08-27T04:00:00.000Z",
    "active_cases": 8340
  },
  {
    "day": "2018-09-03T04:00:00.000Z",
    "active_cases": 8388
  },
  {
    "day": "2018-09-10T04:00:00.000Z",
    "active_cases": 8453
  },
  {
    "day": "2018-09-17T04:00:00.000Z",
    "active_cases": 8523
  },
  {
    "day": "2018-09-24T04:00:00.000Z",
    "active_cases": 8588
  },
  {
    "day": "2018-10-01T04:00:00.000Z",
    "active_cases": 8647
  },
  {
    "day": "2018-10-08T04:00:00.000Z",
    "active_cases": 8713
  },
  {
    "day": "2018-10-15T04:00:00.000Z",
    "active_cases": 8804
  },
  {
    "day": "2018-10-22T04:00:00.000Z",
    "active_cases": 8868
  },
  {
    "day": "2018-10-29T04:00:00.000Z",
    "active_cases": 8958
  },
  {
    "day": "2018-11-05T05:00:00.000Z",
    "active_cases": 9050
  },
  {
    "day": "2018-11-12T05:00:00.000Z",
    "active_cases": 9114
  },
  {
    "day": "2018-11-19T05:00:00.000Z",
    "active_cases": 9205
  },
  {
    "day": "2018-11-26T05:00:00.000Z",
    "active_cases": 9267
  },
  {
    "day": "2018-12-03T05:00:00.000Z",
    "active_cases": 9349
  },
  {
    "day": "2018-12-10T05:00:00.000Z",
    "active_cases": 9438
  },
  {
    "day": "2018-12-17T05:00:00.000Z",
    "active_cases": 9558
  },
  {
    "day": "2018-12-24T05:00:00.000Z",
    "active_cases": 9600
  },
  {
    "day": "2018-12-31T05:00:00.000Z",
    "active_cases": 9668
  },
  {
    "day": "2019-01-07T05:00:00.000Z",
    "active_cases": 9754
  },
  {
    "day": "2019-01-14T05:00:00.000Z",
    "active_cases": 9838
  },
  {
    "day": "2019-01-21T05:00:00.000Z",
    "active_cases": 9926
  },
  {
    "day": "2019-01-28T05:00:00.000Z",
    "active_cases": 9990
  },
  {
    "day": "2019-02-04T05:00:00.000Z",
    "active_cases": 10092
  },
  {
    "day": "2019-02-11T05:00:00.000Z",
    "active_cases": 10178
  },
  {
    "day": "2019-02-18T05:00:00.000Z",
    "active_cases": 10236
  },
  {
    "day": "2019-02-25T05:00:00.000Z",
    "active_cases": 10296
  },
  {
    "day": "2019-03-04T05:00:00.000Z",
    "active_cases": 10355
  },
  {
    "day": "2019-03-11T04:00:00.000Z",
    "active_cases": 10455
  },
  {
    "day": "2019-03-18T04:00:00.000Z",
    "active_cases": 10537
  },
  {
    "day": "2019-03-25T04:00:00.000Z",
    "active_cases": 10595
  },
  {
    "day": "2019-04-01T04:00:00.000Z",
    "active_cases": 10689
  },
  {
    "day": "2019-04-08T04:00:00.000Z",
    "active_cases": 10771
  },
  {
    "day": "2019-04-15T04:00:00.000Z",
    "active_cases": 10831
  },
  {
    "day": "2019-04-22T04:00:00.000Z",
    "active_cases": 10895
  },
  {
    "day": "2019-04-29T04:00:00.000Z",
    "active_cases": 10960
  },
  {
    "day": "2019-05-06T04:00:00.000Z",
    "active_cases": 11057
  },
  {
    "day": "2019-05-13T04:00:00.000Z",
    "active_cases": 11179
  },
  {
    "day": "2019-05-20T04:00:00.000Z",
    "active_cases": 11250
  },
  {
    "day": "2019-05-27T04:00:00.000Z",
    "active_cases": 11296
  },
  {
    "day": "2019-06-03T04:00:00.000Z",
    "active_cases": 11392
  },
  {
    "day": "2019-06-10T04:00:00.000Z",
    "active_cases": 11469
  },
  {
    "day": "2019-06-17T04:00:00.000Z",
    "active_cases": 11538
  },
  {
    "day": "2019-06-24T04:00:00.000Z",
    "active_cases": 11571
  },
  {
    "day": "2019-07-01T04:00:00.000Z",
    "active_cases": 11599
  },
  {
    "day": "2019-07-08T04:00:00.000Z",
    "active_cases": 11643
  },
  {
    "day": "2019-07-15T04:00:00.000Z",
    "active_cases": 11701
  },
  {
    "day": "2019-07-22T04:00:00.000Z",
    "active_cases": 11733
  },
  {
    "day": "2019-07-29T04:00:00.000Z",
    "active_cases": 11803
  },
  {
    "day": "2019-08-05T04:00:00.000Z",
    "active_cases": 11874
  },
  {
    "day": "2019-08-12T04:00:00.000Z",
    "active_cases": 11979
  },
  {
    "day": "2019-08-19T04:00:00.000Z",
    "active_cases": 12062
  },
  {
    "day": "2019-08-26T04:00:00.000Z",
    "active_cases": 12167
  },
  {
    "day": "2019-09-02T04:00:00.000Z",
    "active_cases": 12245
  },
  {
    "day": "2019-09-09T04:00:00.000Z",
    "active_cases": 12346
  },
  {
    "day": "2019-09-16T04:00:00.000Z",
    "active_cases": 12455
  },
  {
    "day": "2019-09-23T04:00:00.000Z",
    "active_cases": 12553
  },
  {
    "day": "2019-09-30T04:00:00.000Z",
    "active_cases": 12680
  },
  {
    "day": "2019-10-07T04:00:00.000Z",
    "active_cases": 12792
  },
  {
    "day": "2019-10-14T04:00:00.000Z",
    "active_cases": 12894
  },
  {
    "day": "2019-10-21T04:00:00.000Z",
    "active_cases": 12999
  },
  {
    "day": "2019-10-28T04:00:00.000Z",
    "active_cases": 13148
  },
  {
    "day": "2019-11-04T05:00:00.000Z",
    "active_cases": 13269
  },
  {
    "day": "2019-11-11T05:00:00.000Z",
    "active_cases": 13377
  },
  {
    "day": "2019-11-18T05:00:00.000Z",
    "active_cases": 13544
  },
  {
    "day": "2019-11-25T05:00:00.000Z",
    "active_cases": 13651
  },
  {
    "day": "2019-12-02T05:00:00.000Z",
    "active_cases": 13811
  },
  {
    "day": "2019-12-09T05:00:00.000Z",
    "active_cases": 14001
  },
  {
    "day": "2019-12-16T05:00:00.000Z",
    "active_cases": 14188
  },
  {
    "day": "2019-12-23T05:00:00.000Z",
    "active_cases": 14274
  },
  {
    "day": "2019-12-30T05:00:00.000Z",
    "active_cases": 14386
  },
  {
    "day": "2020-01-06T05:00:00.000Z",
    "active_cases": 14621
  },
  {
    "day": "2020-01-13T05:00:00.000Z",
    "active_cases": 14868
  },
  {
    "day": "2020-01-20T05:00:00.000Z",
    "active_cases": 15071
  },
  {
    "day": "2020-01-27T05:00:00.000Z",
    "active_cases": 15279
  },
  {
    "day": "2020-02-03T05:00:00.000Z",
    "active_cases": 15548
  },
  {
    "day": "2020-02-10T05:00:00.000Z",
    "active_cases": 15786
  },
  {
    "day": "2020-02-17T05:00:00.000Z",
    "active_cases": 16045
  },
  {
    "day": "2020-02-24T05:00:00.000Z",
    "active_cases": 16325
  },
  {
    "day": "2020-03-02T05:00:00.000Z",
    "active_cases": 16729
  },
  {
    "day": "2020-03-09T04:00:00.000Z",
    "active_cases": 16989
  },
  {
    "day": "2020-03-16T04:00:00.000Z",
    "active_cases": 17162
  },
  {
    "day": "2020-03-23T04:00:00.000Z",
    "active_cases": 17162
  },
  {
    "day": "2020-04-06T04:00:00.000Z",
    "active_cases": 17162
  },
  {
    "day": "2020-04-13T04:00:00.000Z",
    "active_cases": 17163
  },
  {
    "day": "2020-04-27T04:00:00.000Z",
    "active_cases": 17163
  },
  {
    "day": "2020-05-11T04:00:00.000Z",
    "active_cases": 17163
  },
  {
    "day": "2020-05-25T04:00:00.000Z",
    "active_cases": 17163
  },
  {
    "day": "2020-06-01T04:00:00.000Z",
    "active_cases": 17163
  },
  {
    "day": "2020-06-08T04:00:00.000Z",
    "active_cases": 17163
  },
  {
    "day": "2020-06-15T04:00:00.000Z",
    "active_cases": 17163
  },
  {
    "day": "2020-06-22T04:00:00.000Z",
    "active_cases": 17165
  },
  {
    "day": "2020-06-29T04:00:00.000Z",
    "active_cases": 17168
  },
  {
    "day": "2020-07-06T04:00:00.000Z",
    "active_cases": 17183
  },
  {
    "day": "2020-07-13T04:00:00.000Z",
    "active_cases": 17218
  },
  {
    "day": "2020-07-20T04:00:00.000Z",
    "active_cases": 17248
  },
  {
    "day": "2020-07-27T04:00:00.000Z",
    "active_cases": 17322
  },
  {
    "day": "2020-08-03T04:00:00.000Z",
    "active_cases": 17382
  },
  {
    "day": "2020-08-10T04:00:00.000Z",
    "active_cases": 17463
  },
  {
    "day": "2020-08-17T04:00:00.000Z",
    "active_cases": 17562
  },
  {
    "day": "2020-08-24T04:00:00.000Z",
    "active_cases": 17732
  },
  {
    "day": "2020-08-31T04:00:00.000Z",
    "active_cases": 17865
  },
  {
    "day": "2020-09-07T04:00:00.000Z",
    "active_cases": 17982
  },
  {
    "day": "2020-09-14T04:00:00.000Z",
    "active_cases": 18112
  },
  {
    "day": "2020-09-21T04:00:00.000Z",
    "active_cases": 18256
  },
  {
    "day": "2020-09-28T04:00:00.000Z",
    "active_cases": 18377
  },
  {
    "day": "2020-10-05T04:00:00.000Z",
    "active_cases": 18522
  },
  {
    "day": "2020-10-12T04:00:00.000Z",
    "active_cases": 18645
  },
  {
    "day": "2020-10-19T04:00:00.000Z",
    "active_cases": 18786
  },
  {
    "day": "2020-10-26T04:00:00.000Z",
    "active_cases": 18977
  },
  {
    "day": "2020-11-02T05:00:00.000Z",
    "active_cases": 19211
  },
  {
    "day": "2020-11-09T05:00:00.000Z",
    "active_cases": 19371
  },
  {
    "day": "2020-11-16T05:00:00.000Z",
    "active_cases": 19554
  },
  {
    "day": "2020-11-23T05:00:00.000Z",
    "active_cases": 19704
  },
  {
    "day": "2020-11-30T05:00:00.000Z",
    "active_cases": 19862
  },
  {
    "day": "2020-12-07T05:00:00.000Z",
    "active_cases": 20000
  },
  {
    "day": "2020-12-14T05:00:00.000Z",
    "active_cases": 20204
  },
  {
    "day": "2020-12-21T05:00:00.000Z",
    "active_cases": 20395
  },
  {
    "day": "2020-12-28T05:00:00.000Z",
    "active_cases": 20434
  },
  {
    "day": "2021-01-04T05:00:00.000Z",
    "active_cases": 20444
  },
  {
    "day": "2021-01-11T05:00:00.000Z",
    "active_cases": 20466
  },
  {
    "day": "2021-01-18T05:00:00.000Z",
    "active_cases": 20481
  },
  {
    "day": "2021-01-25T05:00:00.000Z",
    "active_cases": 20503
  },
  {
    "day": "2021-02-01T05:00:00.000Z",
    "active_cases": 20525
  },
  {
    "day": "2021-02-08T05:00:00.000Z",
    "active_cases": 20568
  },
  {
    "day": "2021-02-15T05:00:00.000Z",
    "active_cases": 20604
  },
  {
    "day": "2021-02-22T05:00:00.000Z",
    "active_cases": 20694
  },
  {
    "day": "2021-03-01T05:00:00.000Z",
    "active_cases": 20787
  },
  {
    "day": "2021-03-08T05:00:00.000Z",
    "active_cases": 20865
  },
  {
    "day": "2021-03-15T04:00:00.000Z",
    "active_cases": 20922
  },
  {
    "day": "2021-03-22T04:00:00.000Z",
    "active_cases": 21043
  },
  {
    "day": "2021-03-29T04:00:00.000Z",
    "active_cases": 21194
  },
  {
    "day": "2021-04-05T04:00:00.000Z",
    "active_cases": 21334
  },
  {
    "day": "2021-04-12T04:00:00.000Z",
    "active_cases": 21440
  },
  {
    "day": "2021-04-19T04:00:00.000Z",
    "active_cases": 21574
  },
  {
    "day": "2021-04-26T04:00:00.000Z",
    "active_cases": 21719
  },
  {
    "day": "2021-05-03T04:00:00.000Z",
    "active_cases": 21869
  },
  {
    "day": "2021-05-10T04:00:00.000Z",
    "active_cases": 22028
  },
  {
    "day": "2021-05-17T04:00:00.000Z",
    "active_cases": 22200
  },
  {
    "day": "2021-05-24T04:00:00.000Z",
    "active_cases": 22320
  },
  {
    "day": "2021-05-31T04:00:00.000Z",
    "active_cases": 22446
  },
  {
    "day": "2021-06-07T04:00:00.000Z",
    "active_cases": 22629
  },
  {
    "day": "2021-06-14T04:00:00.000Z",
    "active_cases": 22745
  },
  {
    "day": "2021-06-21T04:00:00.000Z",
    "active_cases": 22853
  },
  {
    "day": "2021-06-28T04:00:00.000Z",
    "active_cases": 22970
  },
  {
    "day": "2021-07-05T04:00:00.000Z",
    "active_cases": 23058
  },
  {
    "day": "2021-07-12T04:00:00.000Z",
    "active_cases": 23165
  },
  {
    "day": "2021-07-19T04:00:00.000Z",
    "active_cases": 23287
  },
  {
    "day": "2021-07-26T04:00:00.000Z",
    "active_cases": 23388
  },
  {
    "day": "2021-08-02T04:00:00.000Z",
    "active_cases": 23507
  },
  {
    "day": "2021-08-09T04:00:00.000Z",
    "active_cases": 23656
  },
  {
    "day": "2021-08-16T04:00:00.000Z",
    "active_cases": 23801
  },
  {
    "day": "2021-08-23T04:00:00.000Z",
    "active_cases": 24007
  },
  {
    "day": "2021-08-30T04:00:00.000Z",
    "active_cases": 24111
  },
  {
    "day": "2021-09-06T04:00:00.000Z",
    "active_cases": 24145
  },
  {
    "day": "2021-09-13T04:00:00.000Z",
    "active_cases": 24209
  },
  {
    "day": "2021-09-20T04:00:00.000Z",
    "active_cases": 24312
  },
  {
    "day": "2021-09-27T04:00:00.000Z",
    "active_cases": 24417
  },
  {
    "day": "2021-10-04T04:00:00.000Z",
    "active_cases": 24534
  },
  {
    "day": "2021-10-11T04:00:00.000Z",
    "active_cases": 24657
  },
  {
    "day": "2021-10-18T04:00:00.000Z",
    "active_cases": 24783
  },
  {
    "day": "2021-10-25T04:00:00.000Z",
    "active_cases": 24878
  },
  {
    "day": "2021-11-01T04:00:00.000Z",
    "active_cases": 25017
  },
  {
    "day": "2021-11-08T05:00:00.000Z",
    "active_cases": 25119
  },
  {
    "day": "2021-11-15T05:00:00.000Z",
    "active_cases": 25254
  },
  {
    "day": "2021-11-22T05:00:00.000Z",
    "active_cases": 25337
  },
  {
    "day": "2021-11-29T05:00:00.000Z",
    "active_cases": 25493
  },
  {
    "day": "2021-12-06T05:00:00.000Z",
    "active_cases": 25621
  },
  {
    "day": "2021-12-13T05:00:00.000Z",
    "active_cases": 25739
  },
  {
    "day": "2021-12-20T05:00:00.000Z",
    "active_cases": 25810
  },
  {
    "day": "2021-12-27T05:00:00.000Z",
    "active_cases": 25922
  },
  {
    "day": "2022-01-03T05:00:00.000Z",
    "active_cases": 26013
  },
  {
    "day": "2022-01-10T05:00:00.000Z",
    "active_cases": 26166
  },
  {
    "day": "2022-01-17T05:00:00.000Z",
    "active_cases": 26587
  },
  {
    "day": "2022-01-24T05:00:00.000Z",
    "active_cases": 27081
  },
  {
    "day": "2022-01-31T05:00:00.000Z",
    "active_cases": 27565
  },
  {
    "day": "2022-02-07T05:00:00.000Z",
    "active_cases": 28129
  },
  {
    "day": "2022-02-14T05:00:00.000Z",
    "active_cases": 28720
  },
  {
    "day": "2022-02-21T05:00:00.000Z",
    "active_cases": 29364
  },
  {
    "day": "2022-02-28T05:00:00.000Z",
    "active_cases": 29926
  },
  {
    "day": "2022-03-07T05:00:00.000Z",
    "active_cases": 30662
  },
  {
    "day": "2022-03-14T04:00:00.000Z",
    "active_cases": 31452
  },
  {
    "day": "2022-03-21T04:00:00.000Z",
    "active_cases": 32158
  },
  {
    "day": "2022-03-28T04:00:00.000Z",
    "active_cases": 32873
  },
  {
    "day": "2022-04-04T04:00:00.000Z",
    "active_cases": 33600
  },
  {
    "day": "2022-04-11T04:00:00.000Z",
    "active_cases": 34339
  },
  {
    "day": "2022-04-18T04:00:00.000Z",
    "active_cases": 35188
  },
  {
    "day": "2022-04-25T04:00:00.000Z",
    "active_cases": 35962
  },
  {
    "day": "2022-05-02T04:00:00.000Z",
    "active_cases": 36733
  },
  {
    "day": "2022-05-09T04:00:00.000Z",
    "active_cases": 37595
  },
  {
    "day": "2022-05-16T04:00:00.000Z",
    "active_cases": 38379
  },
  {
    "day": "2022-05-23T04:00:00.000Z",
    "active_cases": 39090
  },
  {
    "day": "2022-05-30T04:00:00.000Z",
    "active_cases": 39688
  },
  {
    "day": "2022-06-06T04:00:00.000Z",
    "active_cases": 40683
  },
  {
    "day": "2022-06-13T04:00:00.000Z",
    "active_cases": 41356
  },
  {
    "day": "2022-06-20T04:00:00.000Z",
    "active_cases": 41882
  },
  {
    "day": "2022-06-27T04:00:00.000Z",
    "active_cases": 42808
  },
  {
    "day": "2022-07-04T04:00:00.000Z",
    "active_cases": 43458
  },
  {
    "day": "2022-07-11T04:00:00.000Z",
    "active_cases": 44176
  },
  {
    "day": "2022-07-18T04:00:00.000Z",
    "active_cases": 45104
  },
  {
    "day": "2022-07-25T04:00:00.000Z",
    "active_cases": 45748
  },
  {
    "day": "2022-08-01T04:00:00.000Z",
    "active_cases": 46430
  },
  {
    "day": "2022-08-08T04:00:00.000Z",
    "active_cases": 47134
  },
  {
    "day": "2022-08-15T04:00:00.000Z",
    "active_cases": 47687
  },
  {
    "day": "2022-08-22T04:00:00.000Z",
    "active_cases": 48130
  },
  {
    "day": "2022-08-29T04:00:00.000Z",
    "active_cases": 48771
  },
  {
    "day": "2022-09-05T04:00:00.000Z",
    "active_cases": 49346
  },
  {
    "day": "2022-09-12T04:00:00.000Z",
    "active_cases": 49992
  },
  {
    "day": "2022-09-19T04:00:00.000Z",
    "active_cases": 50719
  },
  {
    "day": "2022-09-26T04:00:00.000Z",
    "active_cases": 51324
  },
  {
    "day": "2022-10-03T04:00:00.000Z",
    "active_cases": 51942
  },
  {
    "day": "2022-10-10T04:00:00.000Z",
    "active_cases": 52616
  },
  {
    "day": "2022-10-17T04:00:00.000Z",
    "active_cases": 53206
  },
  {
    "day": "2022-10-24T04:00:00.000Z",
    "active_cases": 53782
  },
  {
    "day": "2022-10-31T04:00:00.000Z",
    "active_cases": 54476
  },
  {
    "day": "2022-11-07T05:00:00.000Z",
    "active_cases": 55116
  },
  {
    "day": "2022-11-14T05:00:00.000Z",
    "active_cases": 55686
  },
  {
    "day": "2022-11-21T05:00:00.000Z",
    "active_cases": 56137
  },
  {
    "day": "2022-11-28T05:00:00.000Z",
    "active_cases": 56839
  },
  {
    "day": "2022-12-05T05:00:00.000Z",
    "active_cases": 57473
  },
  {
    "day": "2022-12-12T05:00:00.000Z",
    "active_cases": 58102
  },
  {
    "day": "2022-12-19T05:00:00.000Z",
    "active_cases": 58786
  },
  {
    "day": "2022-12-26T05:00:00.000Z",
    "active_cases": 59334
  },
  {
    "day": "2023-01-02T05:00:00.000Z",
    "active_cases": 59840
  },
  {
    "day": "2023-01-09T05:00:00.000Z",
    "active_cases": 60766
  },
  {
    "day": "2023-01-16T05:00:00.000Z",
    "active_cases": 61433
  },
  {
    "day": "2023-01-23T05:00:00.000Z",
    "active_cases": 62127
  },
  {
    "day": "2023-01-30T05:00:00.000Z",
    "active_cases": 62696
  },
  {
    "day": "2023-02-06T05:00:00.000Z",
    "active_cases": 63294
  },
  {
    "day": "2023-02-13T05:00:00.000Z",
    "active_cases": 63837
  },
  {
    "day": "2023-02-20T05:00:00.000Z",
    "active_cases": 64385
  },
  {
    "day": "2023-02-27T05:00:00.000Z",
    "active_cases": 65048
  },
  {
    "day": "2023-03-06T05:00:00.000Z",
    "active_cases": 65776
  },
  {
    "day": "2023-03-13T04:00:00.000Z",
    "active_cases": 66471
  },
  {
    "day": "2023-03-20T04:00:00.000Z",
    "active_cases": 67128
  },
  {
    "day": "2023-03-27T04:00:00.000Z",
    "active_cases": 67769
  },
  {
    "day": "2023-04-03T04:00:00.000Z",
    "active_cases": 68278
  },
  {
    "day": "2023-04-10T04:00:00.000Z",
    "active_cases": 68935
  },
  {
    "day": "2023-04-17T04:00:00.000Z",
    "active_cases": 69633
  },
  {
    "day": "2023-04-24T04:00:00.000Z",
    "active_cases": 70393
  },
  {
    "day": "2023-05-01T04:00:00.000Z",
    "active_cases": 71197
  },
  {
    "day": "2023-05-08T04:00:00.000Z",
    "active_cases": 71793
  },
  {
    "day": "2023-05-15T04:00:00.000Z",
    "active_cases": 72371
  },
  {
    "day": "2023-05-22T04:00:00.000Z",
    "active_cases": 73013
  },
  {
    "day": "2023-05-29T04:00:00.000Z",
    "active_cases": 73671
  },
  {
    "day": "2023-06-05T04:00:00.000Z",
    "active_cases": 74416
  },
  {
    "day": "2023-06-12T04:00:00.000Z",
    "active_cases": 75053
  },
  {
    "day": "2023-06-19T04:00:00.000Z",
    "active_cases": 75647
  },
  {
    "day": "2023-06-26T04:00:00.000Z",
    "active_cases": 76351
  },
  {
    "day": "2023-07-03T04:00:00.000Z",
    "active_cases": 76925
  },
  {
    "day": "2023-07-10T04:00:00.000Z",
    "active_cases": 77701
  },
  {
    "day": "2023-07-17T04:00:00.000Z",
    "active_cases": 78311
  },
  {
    "day": "2023-07-24T04:00:00.000Z",
    "active_cases": 78961
  },
  {
    "day": "2023-07-31T04:00:00.000Z",
    "active_cases": 79707
  },
  {
    "day": "2023-08-07T04:00:00.000Z",
    "active_cases": 80430
  },
  {
    "day": "2023-08-14T04:00:00.000Z",
    "active_cases": 81118
  },
  {
    "day": "2023-08-21T04:00:00.000Z",
    "active_cases": 81682
  },
  {
    "day": "2023-08-28T04:00:00.000Z",
    "active_cases": 82345
  },
  {
    "day": "2023-09-04T04:00:00.000Z",
    "active_cases": 83013
  },
  {
    "day": "2023-09-11T04:00:00.000Z",
    "active_cases": 83738
  },
  {
    "day": "2023-09-18T04:00:00.000Z",
    "active_cases": 84516
  },
  {
    "day": "2023-09-25T04:00:00.000Z",
    "active_cases": 85203
  },
  {
    "day": "2023-10-02T04:00:00.000Z",
    "active_cases": 85955
  },
  {
    "day": "2023-10-09T04:00:00.000Z",
    "active_cases": 86653
  },
  {
    "day": "2023-10-16T04:00:00.000Z",
    "active_cases": 87643
  },
  {
    "day": "2023-10-23T04:00:00.000Z",
    "active_cases": 88463
  },
  {
    "day": "2023-10-30T04:00:00.000Z",
    "active_cases": 89295
  },
  {
    "day": "2023-11-06T05:00:00.000Z",
    "active_cases": 90365
  },
  {
    "day": "2023-11-13T05:00:00.000Z",
    "active_cases": 91324
  },
  {
    "day": "2023-11-20T05:00:00.000Z",
    "active_cases": 91924
  },
  {
    "day": "2023-11-27T05:00:00.000Z",
    "active_cases": 93005
  },
  {
    "day": "2023-12-04T05:00:00.000Z",
    "active_cases": 94231
  },
  {
    "day": "2023-12-11T05:00:00.000Z",
    "active_cases": 95376
  },
  {
    "day": "2023-12-18T05:00:00.000Z",
    "active_cases": 96348
  },
  {
    "day": "2023-12-25T05:00:00.000Z",
    "active_cases": 97228
  },
  {
    "day": "2024-01-01T05:00:00.000Z",
    "active_cases": 98200
  },
  {
    "day": "2024-01-08T05:00:00.000Z",
    "active_cases": 99574
  },
  {
    "day": "2024-01-15T05:00:00.000Z",
    "active_cases": 100675
  },
  {
    "day": "2024-01-22T05:00:00.000Z",
    "active_cases": 101779
  },
  {
    "day": "2024-01-29T05:00:00.000Z",
    "active_cases": 102980
  },
  {
    "day": "2024-02-05T05:00:00.000Z",
    "active_cases": 104425
  },
  {
    "day": "2024-02-12T05:00:00.000Z",
    "active_cases": 105819
  },
  {
    "day": "2024-02-19T05:00:00.000Z",
    "active_cases": 107047
  },
  {
    "day": "2024-02-26T05:00:00.000Z",
    "active_cases": 108633
  },
  {
    "day": "2024-03-04T05:00:00.000Z",
    "active_cases": 110492
  },
  {
    "day": "2024-03-11T04:00:00.000Z",
    "active_cases": 112326
  },
  {
    "day": "2024-03-18T04:00:00.000Z",
    "active_cases": 114244
  },
  {
    "day": "2024-03-25T04:00:00.000Z",
    "active_cases": 116167
  },
  {
    "day": "2024-04-01T04:00:00.000Z",
    "active_cases": 118051
  },
  {
    "day": "2024-04-08T04:00:00.000Z",
    "active_cases": 120289
  },
  {
    "day": "2024-04-15T04:00:00.000Z",
    "active_cases": 122165
  },
  {
    "day": "2024-04-22T04:00:00.000Z",
    "active_cases": 124003
  },
  {
    "day": "2024-04-29T04:00:00.000Z",
    "active_cases": 126112
  },
  {
    "day": "2024-05-06T04:00:00.000Z",
    "active_cases": 128532
  },
  {
    "day": "2024-05-13T04:00:00.000Z",
    "active_cases": 130997
  },
  {
    "day": "2024-05-20T04:00:00.000Z",
    "active_cases": 133159
  },
  {
    "day": "2024-05-27T04:00:00.000Z",
    "active_cases": 134939
  },
  {
    "day": "2024-06-03T04:00:00.000Z",
    "active_cases": 137792
  },
  {
    "day": "2024-06-10T04:00:00.000Z",
    "active_cases": 140249
  },
  {
    "day": "2024-06-17T04:00:00.000Z",
    "active_cases": 142457
  },
  {
    "day": "2024-06-24T04:00:00.000Z",
    "active_cases": 144653
  },
  {
    "day": "2024-07-01T04:00:00.000Z",
    "active_cases": 146546
  },
  {
    "day": "2024-07-08T04:00:00.000Z",
    "active_cases": 149308
  },
  {
    "day": "2024-07-15T04:00:00.000Z",
    "active_cases": 152074
  },
  {
    "day": "2024-07-22T04:00:00.000Z",
    "active_cases": 154401
  },
  {
    "day": "2024-07-29T04:00:00.000Z",
    "active_cases": 156609
  },
  {
    "day": "2024-08-05T04:00:00.000Z",
    "active_cases": 158376
  }
]