[
  {
    "day": "2015-12-28T05:00:00.000Z",
    "active_cases": 0
  },
  {
    "day": "2016-01-04T05:00:00.000Z",
    "active_cases": 127
  },
  {
    "day": "2016-01-11T05:00:00.000Z",
    "active_cases": 265
  },
  {
    "day": "2016-01-18T05:00:00.000Z",
    "active_cases": 346
  },
  {
    "day": "2016-01-25T05:00:00.000Z",
    "active_cases": 450
  },
  {
    "day": "2016-02-01T05:00:00.000Z",
    "active_cases": 582
  },
  {
    "day": "2016-02-08T05:00:00.000Z",
    "active_cases": 675
  },
  {
    "day": "2016-02-15T05:00:00.000Z",
    "active_cases": 846
  },
  {
    "day": "2016-02-22T05:00:00.000Z",
    "active_cases": 999
  },
  {
    "day": "2016-02-29T05:00:00.000Z",
    "active_cases": 1120
  },
  {
    "day": "2016-03-07T05:00:00.000Z",
    "active_cases": 1227
  },
  {
    "day": "2016-03-14T04:00:00.000Z",
    "active_cases": 1333
  },
  {
    "day": "2016-03-21T04:00:00.000Z",
    "active_cases": 1455
  },
  {
    "day": "2016-03-28T04:00:00.000Z",
    "active_cases": 1543
  },
  {
    "day": "2016-04-04T04:00:00.000Z",
    "active_cases": 1637
  },
  {
    "day": "2016-04-11T04:00:00.000Z",
    "active_cases": 1743
  },
  {
    "day": "2016-04-18T04:00:00.000Z",
    "active_cases": 1830
  },
  {
    "day": "2016-04-25T04:00:00.000Z",
    "active_cases": 1939
  },
  {
    "day": "2016-05-02T04:00:00.000Z",
    "active_cases": 2032
  },
  {
    "day": "2016-05-09T04:00:00.000Z",
    "active_cases": 2142
  },
  {
    "day": "2016-05-16T04:00:00.000Z",
    "active_cases": 2223
  },
  {
    "day": "2016-05-23T04:00:00.000Z",
    "active_cases": 2322
  },
  {
    "day": "2016-05-30T04:00:00.000Z",
    "active_cases": 2396
  },
  {
    "day": "2016-06-06T04:00:00.000Z",
    "active_cases": 2502
  },
  {
    "day": "2016-06-13T04:00:00.000Z",
    "active_cases": 2624
  },
  {
    "day": "2016-06-20T04:00:00.000Z",
    "active_cases": 2726
  },
  {
    "day": "2016-06-27T04:00:00.000Z",
    "active_cases": 2832
  },
  {
    "day": "2016-07-04T04:00:00.000Z",
    "active_cases": 2914
  },
  {
    "day": "2016-07-11T04:00:00.000Z",
    "active_cases": 3051
  },
  {
    "day": "2016-07-18T04:00:00.000Z",
    "active_cases": 3188
  },
  {
    "day": "2016-07-25T04:00:00.000Z",
    "active_cases": 3280
  },
  {
    "day": "2016-08-01T04:00:00.000Z",
    "active_cases": 3373
  },
  {
    "day": "2016-08-08T04:00:00.000Z",
    "active_cases": 3510
  },
  {
    "day": "2016-08-15T04:00:00.000Z",
    "active_cases": 3615
  },
  {
    "day": "2016-08-22T04:00:00.000Z",
    "active_cases": 3713
  },
  {
    "day": "2016-08-29T04:00:00.000Z",
    "active_cases": 3796
  },
  {
    "day": "2016-09-05T04:00:00.000Z",
    "active_cases": 3881
  },
  {
    "day": "2016-09-12T04:00:00.000Z",
    "active_cases": 4003
  },
  {
    "day": "2016-09-19T04:00:00.000Z",
    "active_cases": 4140
  },
  {
    "day": "2016-09-26T04:00:00.000Z",
    "active_cases": 4256
  },
  {
    "day": "2016-10-03T04:00:00.000Z",
    "active_cases": 4371
  },
  {
    "day": "2016-10-10T04:00:00.000Z",
    "active_cases": 4476
  },
  {
    "day": "2016-10-17T04:00:00.000Z",
    "active_cases": 4609
  },
  {
    "day": "2016-10-24T04:00:00.000Z",
    "active_cases": 4684
  },
  {
    "day": "2016-10-31T04:00:00.000Z",
    "active_cases": 4797
  },
  {
    "day": "2016-11-07T05:00:00.000Z",
    "active_cases": 4913
  },
  {
    "day": "2016-11-14T05:00:00.000Z",
    "active_cases": 5053
  },
  {
    "day": "2016-11-21T05:00:00.000Z",
    "active_cases": 5169
  },
  {
    "day": "2016-11-28T05:00:00.000Z",
    "active_cases": 5287
  },
  {
    "day": "2016-12-05T05:00:00.000Z",
    "active_cases": 5426
  },
  {
    "day": "2016-12-12T05:00:00.000Z",
    "active_cases": 5545
  },
  {
    "day": "2016-12-19T05:00:00.000Z",
    "active_cases": 5654
  },
  {
    "day": "2016-12-26T05:00:00.000Z",
    "active_cases": 5736
  },
  {
    "day": "2017-01-02T05:00:00.000Z",
    "active_cases": 5804
  },
  {
    "day": "2017-01-09T05:00:00.000Z",
    "active_cases": 5922
  },
  {
    "day": "2017-01-16T05:00:00.000Z",
    "active_cases": 6025
  },
  {
    "day": "2017-01-23T05:00:00.000Z",
    "active_cases": 6150
  },
  {
    "day": "2017-01-30T05:00:00.000Z",
    "active_cases": 6289
  },
  {
    "day": "2017-02-06T05:00:00.000Z",
    "active_cases": 6428
  },
  {
    "day": "2017-02-13T05:00:00.000Z",
    "active_cases": 6539
  },
  {
    "day": "2017-02-20T05:00:00.000Z",
    "active_cases": 6639
  },
  {
    "day": "2017-02-27T05:00:00.000Z",
    "active_cases": 6737
  },
  {
    "day": "2017-03-06T05:00:00.000Z",
    "active_cases": 6845
  },
  {
    "day": "2017-03-13T04:00:00.000Z",
    "active_cases": 6934
  },
  {
    "day": "2017-03-20T04:00:00.000Z",
    "active_cases": 7043
  },
  {
    "day": "2017-03-27T04:00:00.000Z",
    "active_cases": 7136
  },
  {
    "day": "2017-04-03T04:00:00.000Z",
    "active_cases": 7258
  },
  {
    "day": "2017-04-10T04:00:00.000Z",
    "active_cases": 7363
  },
  {
    "day": "2017-04-17T04:00:00.000Z",
    "active_cases": 7436
  },
  {
    "day": "2017-04-24T04:00:00.000Z",
    "active_cases": 7530
  },
  {
    "day": "2017-05-01T04:00:00.000Z",
    "active_cases": 7618
  },
  {
    "day": "2017-05-08T04:00:00.000Z",
    "active_cases": 7726
  },
  {
    "day": "2017-05-15T04:00:00.000Z",
    "active_cases": 7809
  },
  {
    "day": "2017-05-22T04:00:00.000Z",
    "active_cases": 7900
  },
  {
    "day": "2017-05-29T04:00:00.000Z",
    "active_cases": 7965
  },
  {
    "day": "2017-06-05T04:00:00.000Z",
    "active_cases": 8075
  },
  {
    "day": "2017-06-12T04:00:00.000Z",
    "active_cases": 8174
  },
  {
    "day": "2017-06-19T04:00:00.000Z",
    "active_cases": 8262
  },
  {
    "day": "2017-06-26T04:00:00.000Z",
    "active_cases": 8361
  },
  {
    "day": "2017-07-03T04:00:00.000Z",
    "active_cases": 8407
  },
  {
    "day": "2017-07-10T04:00:00.000Z",
    "active_cases": 8551
  },
  {
    "day": "2017-07-17T04:00:00.000Z",
    "active_cases": 8656
  },
  {
    "day": "2017-07-24T04:00:00.000Z",
    "active_cases": 8749
  },
  {
    "day": "2017-07-31T04:00:00.000Z",
    "active_cases": 8839
  },
  {
    "day": "2017-08-07T04:00:00.000Z",
    "active_cases": 8983
  },
  {
    "day": "2017-08-14T04:00:00.000Z",
    "active_cases": 9068
  },
  {
    "day": "2017-08-21T04:00:00.000Z",
    "active_cases": 9162
  },
  {
    "day": "2017-08-28T04:00:00.000Z",
    "active_cases": 9248
  },
  {
    "day": "2017-09-04T04:00:00.000Z",
    "active_cases": 9333
  },
  {
    "day": "2017-09-11T04:00:00.000Z",
    "active_cases": 9439
  },
  {
    "day": "2017-09-18T04:00:00.000Z",
    "active_cases": 9544
  },
  {
    "day": "2017-09-25T04:00:00.000Z",
    "active_cases": 9636
  },
  {
    "day": "2017-10-02T04:00:00.000Z",
    "active_cases": 9735
  },
  {
    "day": "2017-10-09T04:00:00.000Z",
    "active_cases": 9833
  },
  {
    "day": "2017-10-16T04:00:00.000Z",
    "active_cases": 9977
  },
  {
    "day": "2017-10-23T04:00:00.000Z",
    "active_cases": 10072
  },
  {
    "day": "2017-10-30T04:00:00.000Z",
    "active_cases": 10178
  },
  {
    "day": "2017-11-06T05:00:00.000Z",
    "active_cases": 10289
  },
  {
    "day": "2017-11-13T05:00:00.000Z",
    "active_cases": 10411
  },
  {
    "day": "2017-11-20T05:00:00.000Z",
    "active_cases": 10471
  },
  {
    "day": "2017-11-27T05:00:00.000Z",
    "active_cases": 10548
  },
  {
    "day": "2017-12-04T05:00:00.000Z",
    "active_cases": 10669
  },
  {
    "day": "2017-12-11T05:00:00.000Z",
    "active_cases": 10780
  },
  {
    "day": "2017-12-18T05:00:00.000Z",
    "active_cases": 10918
  },
  {
    "day": "2017-12-25T05:00:00.000Z",
    "active_cases": 10986
  },
  {
    "day": "2018-01-01T05:00:00.000Z",
    "active_cases": 11099
  },
  {
    "day": "2018-01-08T05:00:00.000Z",
    "active_cases": 11286
  },
  {
    "day": "2018-01-15T05:00:00.000Z",
    "active_cases": 11445
  },
  {
    "day": "2018-01-22T05:00:00.000Z",
    "active_cases": 11613
  },
  {
    "day": "2018-01-29T05:00:00.000Z",
    "active_cases": 11779
  },
  {
    "day": "2018-02-05T05:00:00.000Z",
    "active_cases": 11981
  },
  {
    "day": "2018-02-12T05:00:00.000Z",
    "active_cases": 12165
  },
  {
    "day": "2018-02-19T05:00:00.000Z",
    "active_cases": 12291
  },
  {
    "day": "2018-02-26T05:00:00.000Z",
    "active_cases": 12422
  },
  {
    "day": "2018-03-05T05:00:00.000Z",
    "active_cases": 12653
  },
  {
    "day": "2018-03-12T04:00:00.000Z",
    "active_cases": 12804
  },
  {
    "day": "2018-03-19T04:00:00.000Z",
    "active_cases": 12924
  },
  {
    "day": "2018-03-26T04:00:00.000Z",
    "active_cases": 13075
  },
  {
    "day": "2018-04-02T04:00:00.000Z",
    "active_cases": 13261
  },
  {
    "day": "2018-04-09T04:00:00.000Z",
    "active_cases": 13434
  },
  {
    "day": "2018-04-16T04:00:00.000Z",
    "active_cases": 13553
  },
  {
    "day": "2018-04-23T04:00:00.000Z",
    "active_cases": 13653
  },
  {
    "day": "2018-04-30T04:00:00.000Z",
    "active_cases": 13845
  },
  {
    "day": "2018-05-07T04:00:00.000Z",
    "active_cases": 14036
  },
  {
    "day": "2018-05-14T04:00:00.000Z",
    "active_cases": 14166
  },
  {
    "day": "2018-05-21T04:00:00.000Z",
    "active_cases": 14290
  },
  {
    "day": "2018-05-28T04:00:00.000Z",
    "active_cases": 14389
  },
  {
    "day": "2018-06-04T04:00:00.000Z",
    "active_cases": 14602
  },
  {
    "day": "2018-06-11T04:00:00.000Z",
    "active_cases": 14780
  },
  {
    "day": "2018-06-18T04:00:00.000Z",
    "active_cases": 14936
  },
  {
    "day": "2018-06-25T04:00:00.000Z",
    "active_cases": 15068
  },
  {
    "day": "2018-07-02T04:00:00.000Z",
    "active_cases": 15186
  },
  {
    "day": "2018-07-09T04:00:00.000Z",
    "active_cases": 15411
  },
  {
    "day": "2018-07-16T04:00:00.000Z",
    "active_cases": 15608
  },
  {
    "day": "2018-07-23T04:00:00.000Z",
    "active_cases": 15773
  },
  {
    "day": "2018-07-30T04:00:00.000Z",
    "active_cases": 15938
  },
  {
    "day": "2018-08-06T04:00:00.000Z",
    "active_cases": 16128
  },
  {
    "day": "2018-08-13T04:00:00.000Z",
    "active_cases": 16302
  },
  {
    "day": "2018-08-20T04:00:00.000Z",
    "active_cases": 16477
  },
  {
    "day": "2018-08-27T04:00:00.000Z",
    "active_cases": 16614
  },
  {
    "day": "2018-09-03T04:00:00.000Z",
    "active_cases": 16758
  },
  {
    "day": "2018-09-10T04:00:00.000Z",
    "active_cases": 16926
  },
  {
    "day": "2018-09-17T04:00:00.000Z",
    "active_cases": 17081
  },
  {
    "day": "2018-09-24T04:00:00.000Z",
    "active_cases": 17217
  },
  {
    "day": "2018-10-01T04:00:00.000Z",
    "active_cases": 17394
  },
  {
    "day": "2018-10-08T04:00:00.000Z",
    "active_cases": 17567
  },
  {
    "day": "2018-10-15T04:00:00.000Z",
    "active_cases": 17761
  },
  {
    "day": "2018-10-22T04:00:00.000Z",
    "active_cases": 17897
  },
  {
    "day": "2018-10-29T04:00:00.000Z",
    "active_cases": 18067
  },
  {
    "day": "2018-11-05T05:00:00.000Z",
    "active_cases": 18288
  },
  {
    "day": "2018-11-12T05:00:00.000Z",
    "active_cases": 18438
  },
  {
    "day": "2018-11-19T05:00:00.000Z",
    "active_cases": 18599
  },
  {
    "day": "2018-11-26T05:00:00.000Z",
    "active_cases": 18727
  },
  {
    "day": "2018-12-03T05:00:00.000Z",
    "active_cases": 18936
  },
  {
    "day": "2018-12-10T05:00:00.000Z",
    "active_cases": 19144
  },
  {
    "day": "2018-12-17T05:00:00.000Z",
    "active_cases": 19355
  },
  {
    "day": "2018-12-24T05:00:00.000Z",
    "active_cases": 19447
  },
  {
    "day": "2018-12-31T05:00:00.000Z",
    "active_cases": 19584
  },
  {
    "day": "2019-01-07T05:00:00.000Z",
    "active_cases": 19792
  },
  {
    "day": "2019-01-14T05:00:00.000Z",
    "active_cases": 19970
  },
  {
    "day": "2019-01-21T05:00:00.000Z",
    "active_cases": 20116
  },
  {
    "day": "2019-01-28T05:00:00.000Z",
    "active_cases": 20246
  },
  {
    "day": "2019-02-04T05:00:00.000Z",
    "active_cases": 20453
  },
  {
    "day": "2019-02-11T05:00:00.000Z",
    "active_cases": 20623
  },
  {
    "day": "2019-02-18T05:00:00.000Z",
    "active_cases": 20760
  },
  {
    "day": "2019-02-25T05:00:00.000Z",
    "active_cases": 20915
  },
  {
    "day": "2019-03-04T05:00:00.000Z",
    "active_cases": 21083
  },
  {
    "day": "2019-03-11T04:00:00.000Z",
    "active_cases": 21269
  },
  {
    "day": "2019-03-18T04:00:00.000Z",
    "active_cases": 21424
  },
  {
    "day": "2019-03-25T04:00:00.000Z",
    "active_cases": 21539
  },
  {
    "day": "2019-04-01T04:00:00.000Z",
    "active_cases": 21733
  },
  {
    "day": "2019-04-08T04:00:00.000Z",
    "active_cases": 21893
  },
  {
    "day": "2019-04-15T04:00:00.000Z",
    "active_cases": 22027
  },
  {
    "day": "2019-04-22T04:00:00.000Z",
    "active_cases": 22173
  },
  {
    "day": "2019-04-29T04:00:00.000Z",
    "active_cases": 22328
  },
  {
    "day": "2019-05-06T04:00:00.000Z",
    "active_cases": 22533
  },
  {
    "day": "2019-05-13T04:00:00.000Z",
    "active_cases": 22730
  },
  {
    "day": "2019-05-20T04:00:00.000Z",
    "active_cases": 22876
  },
  {
    "day": "2019-05-27T04:00:00.000Z",
    "active_cases": 22972
  },
  {
    "day": "2019-06-03T04:00:00.000Z",
    "active_cases": 23160
  },
  {
    "day": "2019-06-10T04:00:00.000Z",
    "active_cases": 23323
  },
  {
    "day": "2019-06-17T04:00:00.000Z",
    "active_cases": 23451
  },
  {
    "day": "2019-06-24T04:00:00.000Z",
    "active_cases": 23535
  },
  {
    "day": "2019-07-01T04:00:00.000Z",
    "active_cases": 23612
  },
  {
    "day": "2019-07-08T04:00:00.000Z",
    "active_cases": 23714
  },
  {
    "day": "2019-07-15T04:00:00.000Z",
    "active_cases": 23839
  },
  {
    "day": "2019-07-22T04:00:00.000Z",
    "active_cases": 23912
  },
  {
    "day": "2019-07-29T04:00:00.000Z",
    "active_cases": 24053
  },
  {
    "day": "2019-08-05T04:00:00.000Z",
    "active_cases": 24227
  },
  {
    "day": "2019-08-12T04:00:00.000Z",
    "active_cases": 24428
  },
  {
    "day": "2019-08-19T04:00:00.000Z",
    "active_cases": 24618
  },
  {
    "day": "2019-08-26T04:00:00.000Z",
    "active_cases": 24818
  },
  {
    "day": "2019-09-02T04:00:00.000Z",
    "active_cases": 25013
  },
  {
    "day": "2019-09-09T04:00:00.000Z",
    "active_cases": 25222
  },
  {
    "day": "2019-09-16T04:00:00.000Z",
    "active_cases": 25450
  },
  {
    "day": "2019-09-23T04:00:00.000Z",
    "active_cases": 25662
  },
  {
    "day": "2019-09-30T04:00:00.000Z",
    "active_cases": 25897
  },
  {
    "day": "2019-10-07T04:00:00.000Z",
    "active_cases": 26130
  },
  {
    "day": "2019-10-14T04:00:00.000Z",
    "active_cases": 26358
  },
  {
    "day": "2019-10-21T04:00:00.000Z",
    "active_cases": 26577
  },
  {
    "day": "2019-10-28T04:00:00.000Z",
    "active_cases": 26841
  },
  {
    "day": "2019-11-04T05:00:00.000Z",
    "active_cases": 27089
  },
  {
    "day": "2019-11-11T05:00:00.000Z",
    "active_cases": 27293
  },
  {
    "day": "2019-11-18T05:00:00.000Z",
    "active_cases": 27581
  },
  {
    "day": "2019-11-25T05:00:00.000Z",
    "active_cases": 27777
  },
  {
    "day": "2019-12-02T05:00:00.000Z",
    "active_cases": 28067
  },
  {
    "day": "2019-12-09T05:00:00.000Z",
    "active_cases": 28389
  },
  {
    "day": "2019-12-16T05:00:00.000Z",
    "active_cases": 28693
  },
  {
    "day": "2019-12-23T05:00:00.000Z",
    "active_cases": 28836
  },
  {
    "day": "2019-12-30T05:00:00.000Z",
    "active_cases": 29018
  },
  {
    "day": "2020-01-06T05:00:00.000Z",
    "active_cases": 29381
  },
  {
    "day": "2020-01-13T05:00:00.000Z",
    "active_cases": 29755
  },
  {
    "day": "2020-01-20T05:00:00.000Z",
    "active_cases": 30062
  },
  {
    "day": "2020-01-27T05:00:00.000Z",
    "active_cases": 30372
  },
  {
    "day": "2020-02-03T05:00:00.000Z",
    "active_cases": 30787
  },
  {
    "day": "2020-02-10T05:00:00.000Z",
    "active_cases": 31125
  },
  {
    "day": "2020-02-17T05:00:00.000Z",
    "active_cases": 31484
  },
  {
    "day": "2020-02-24T05:00:00.000Z",
    "active_cases": 31882
  },
  {
    "day": "2020-03-02T05:00:00.000Z",
    "active_cases": 32430
  },
  {
    "day": "2020-03-09T04:00:00.000Z",
    "active_cases": 32779
  },
  {
    "day": "2020-03-16T04:00:00.000Z",
    "active_cases": 32982
  },
  {
    "day": "2020-03-23T04:00:00.000Z",
    "active_cases": 32982
  },
  {
    "day": "2020-04-06T04:00:00.000Z",
    "active_cases": 32982
  },
  {
    "day": "2020-04-13T04:00:00.000Z",
    "active_cases": 32983
  },
  {
    "day": "2020-04-27T04:00:00.000Z",
    "active_cases": 32983
  },
  {
    "day": "2020-05-11T04:00:00.000Z",
    "active_cases": 32983
  },
  {
    "day": "2020-05-25T04:00:00.000Z",
    "active_cases": 32983
  },
  {
    "day": "2020-06-01T04:00:00.000Z",
    "active_cases": 32983
  },
  {
    "day": "2020-06-08T04:00:00.000Z",
    "active_cases": 32983
  },
  {
    "day": "2020-06-15T04:00:00.000Z",
    "active_cases": 32983
  },
  {
    "day": "2020-06-22T04:00:00.000Z",
    "active_cases": 32985
  },
  {
    "day": "2020-06-29T04:00:00.000Z",
    "active_cases": 32988
  },
  {
    "day": "2020-07-06T04:00:00.000Z",
    "active_cases": 33004
  },
  {
    "day": "2020-07-13T04:00:00.000Z",
    "active_cases": 33057
  },
  {
    "day": "2020-07-20T04:00:00.000Z",
    "active_cases": 33107
  },
  {
    "day": "2020-07-27T04:00:00.000Z",
    "active_cases": 33219
  },
  {
    "day": "2020-08-03T04:00:00.000Z",
    "active_cases": 33291
  },
  {
    "day": "2020-08-10T04:00:00.000Z",
    "active_cases": 33402
  },
  {
    "day": "2020-08-17T04:00:00.000Z",
    "active_cases": 33533
  },
  {
    "day": "2020-08-24T04:00:00.000Z",
    "active_cases": 33759
  },
  {
    "day": "2020-08-31T04:00:00.000Z",
    "active_cases": 33948
  },
  {
    "day": "2020-09-07T04:00:00.000Z",
    "active_cases": 34095
  },
  {
    "day": "2020-09-14T04:00:00.000Z",
    "active_cases": 34277
  },
  {
    "day": "2020-09-21T04:00:00.000Z",
    "active_cases": 34471
  },
  {
    "day": "2020-09-28T04:00:00.000Z",
    "active_cases": 34638
  },
  {
    "day": "2020-10-05T04:00:00.000Z",
    "active_cases": 34845
  },
  {
    "day": "2020-10-12T04:00:00.000Z",
    "active_cases": 35016
  },
  {
    "day": "2020-10-19T04:00:00.000Z",
    "active_cases": 35212
  },
  {
    "day": "2020-10-26T04:00:00.000Z",
    "active_cases": 35458
  },
  {
    "day": "2020-11-02T05:00:00.000Z",
    "active_cases": 35780
  },
  {
    "day": "2020-11-09T05:00:00.000Z",
    "active_cases": 36012
  },
  {
    "day": "2020-11-16T05:00:00.000Z",
    "active_cases": 36242
  },
  {
    "day": "2020-11-23T05:00:00.000Z",
    "active_cases": 36434
  },
  {
    "day": "2020-11-30T05:00:00.000Z",
    "active_cases": 36639
  },
  {
    "day": "2020-12-07T05:00:00.000Z",
    "active_cases": 36815
  },
  {
    "day": "2020-12-14T05:00:00.000Z",
    "active_cases": 37078
  },
  {
    "day": "2020-12-21T05:00:00.000Z",
    "active_cases": 37312
  },
  {
    "day": "2020-12-28T05:00:00.000Z",
    "active_cases": 37366
  },
  {
    "day": "2021-01-04T05:00:00.000Z",
    "active_cases": 37381
  },
  {
    "day": "2021-01-11T05:00:00.000Z",
    "active_cases": 37443
  },
  {
    "day": "2021-01-18T05:00:00.000Z",
    "active_cases": 37492
  },
  {
    "day": "2021-01-25T05:00:00.000Z",
    "active_cases": 37536
  },
  {
    "day": "2021-02-01T05:00:00.000Z",
    "active_cases": 37588
  },
  {
    "day": "2021-02-08T05:00:00.000Z",
    "active_cases": 37735
  },
  {
    "day": "2021-02-15T05:00:00.000Z",
    "active_cases": 37869
  },
  {
    "day": "2021-02-22T05:00:00.000Z",
    "active_cases": 38138
  },
  {
    "day": "2021-03-01T05:00:00.000Z",
    "active_cases": 38466
  },
  {
    "day": "2021-03-08T05:00:00.000Z",
    "active_cases": 38739
  },
  {
    "day": "2021-03-15T04:00:00.000Z",
    "active_cases": 38957
  },
  {
    "day": "2021-03-22T04:00:00.000Z",
    "active_cases": 39402
  },
  {
    "day": "2021-03-29T04:00:00.000Z",
    "active_cases": 39855
  },
  {
    "day": "2021-04-05T04:00:00.000Z",
    "active_cases": 40350
  },
  {
    "day": "2021-04-12T04:00:00.000Z",
    "active_cases": 40734
  },
  {
    "day": "2021-04-19T04:00:00.000Z",
    "active_cases": 41163
  },
  {
    "day": "2021-04-26T04:00:00.000Z",
    "active_cases": 41647
  },
  {
    "day": "2021-05-03T04:00:00.000Z",
    "active_cases": 42087
  },
  {
    "day": "2021-05-10T04:00:00.000Z",
    "active_cases": 42743
  },
  {
    "day": "2021-05-17T04:00:00.000Z",
    "active_cases": 43319
  },
  {
    "day": "2021-05-24T04:00:00.000Z",
    "active_cases": 43864
  },
  {
    "day": "2021-05-31T04:00:00.000Z",
    "active_cases": 44257
  },
  {
    "day": "2021-06-07T04:00:00.000Z",
    "active_cases": 44817
  },
  {
    "day": "2021-06-14T04:00:00.000Z",
    "active_cases": 45296
  },
  {
    "day": "2021-06-21T04:00:00.000Z",
    "active_cases": 45757
  },
  {
    "day": "2021-06-28T04:00:00.000Z",
    "active_cases": 46218
  },
  {
    "day": "2021-07-05T04:00:00.000Z",
    "active_cases": 46540
  },
  {
    "day": "2021-07-12T04:00:00.000Z",
    "active_cases": 46922
  },
  {
    "day": "2021-07-19T04:00:00.000Z",
    "active_cases": 47377
  },
  {
    "day": "2021-07-26T04:00:00.000Z",
    "active_cases": 47817
  },
  {
    "day": "2021-08-02T04:00:00.000Z",
    "active_cases": 48176
  },
  {
    "day": "2021-08-09T04:00:00.000Z",
    "active_cases": 48564
  },
  {
    "day": "2021-08-16T04:00:00.000Z",
    "active_cases": 49050
  },
  {
    "day": "2021-08-23T04:00:00.000Z",
    "active_cases": 49608
  },
  {
    "day": "2021-08-30T04:00:00.000Z",
    "active_cases": 49944
  },
  {
    "day": "2021-09-06T04:00:00.000Z",
    "active_cases": 50033
  },
  {
    "day": "2021-09-13T04:00:00.000Z",
    "active_cases": 50240
  },
  {
    "day": "2021-09-20T04:00:00.000Z",
    "active_cases": 50485
  },
  {
    "day": "2021-09-27T04:00:00.000Z",
    "active_cases": 50801
  },
  {
    "day": "2021-10-04T04:00:00.000Z",
    "active_cases": 51118
  },
  {
    "day": "2021-10-11T04:00:00.000Z",
    "active_cases": 51558
  },
  {
    "day": "2021-10-18T04:00:00.000Z",
    "active_cases": 51933
  },
  {
    "day": "2021-10-25T04:00:00.000Z",
    "active_cases": 52213
  },
  {
    "day": "2021-11-01T04:00:00.000Z",
    "active_cases": 52565
  },
  {
    "day": "2021-11-08T05:00:00.000Z",
    "active_cases": 52900
  },
  {
    "day": "2021-11-15T05:00:00.000Z",
    "active_cases": 53282
  },
  {
    "day": "2021-11-22T05:00:00.000Z",
    "active_cases": 53562
  },
  {
    "day": "2021-11-29T05:00:00.000Z",
    "active_cases": 53948
  },
  {
    "day": "2021-12-06T05:00:00.000Z",
    "active_cases": 54322
  },
  {
    "day": "2021-12-13T05:00:00.000Z",
    "active_cases": 54667
  },
  {
    "day": "2021-12-20T05:00:00.000Z",
    "active_cases": 54942
  },
  {
    "day": "2021-12-27T05:00:00.000Z",
    "active_cases": 55301
  },
  {
    "day": "2022-01-03T05:00:00.000Z",
    "active_cases": 55614
  },
  {
    "day": "2022-01-10T05:00:00.000Z",
    "active_cases": 56100
  },
  {
    "day": "2022-01-17T05:00:00.000Z",
    "active_cases": 56571
  },
  {
    "day": "2022-01-24T05:00:00.000Z",
    "active_cases": 57103
  },
  {
    "day": "2022-01-31T05:00:00.000Z",
    "active_cases": 57623
  },
  {
    "day": "2022-02-07T05:00:00.000Z",
    "active_cases": 58219
  },
  {
    "day": "2022-02-14T05:00:00.000Z",
    "active_cases": 58858
  },
  {
    "day": "2022-02-21T05:00:00.000Z",
    "active_cases": 59545
  },
  {
    "day": "2022-02-28T05:00:00.000Z",
    "active_cases": 60150
  },
  {
    "day": "2022-03-07T05:00:00.000Z",
    "active_cases": 60943
  },
  {
    "day": "2022-03-14T04:00:00.000Z",
    "active_cases": 61809
  },
  {
    "day": "2022-03-21T04:00:00.000Z",
    "active_cases": 62555
  },
  {
    "day": "2022-03-28T04:00:00.000Z",
    "active_cases": 63338
  },
  {
    "day": "2022-04-04T04:00:00.000Z",
    "active_cases": 64111
  },
  {
    "day": "2022-04-11T04:00:00.000Z",
    "active_cases": 64910
  },
  {
    "day": "2022-04-18T04:00:00.000Z",
    "active_cases": 65834
  },
  {
    "day": "2022-04-25T04:00:00.000Z",
    "active_cases": 66659
  },
  {
    "day": "2022-05-02T04:00:00.000Z",
    "active_cases": 67513
  },
  {
    "day": "2022-05-09T04:00:00.000Z",
    "active_cases": 68446
  },
  {
    "day": "2022-05-16T04:00:00.000Z",
    "active_cases": 69308
  },
  {
    "day": "2022-05-23T04:00:00.000Z",
    "active_cases": 70091
  },
  {
    "day": "2022-05-30T04:00:00.000Z",
    "active_cases": 70754
  },
  {
    "day": "2022-06-06T04:00:00.000Z",
    "active_cases": 71815
  },
  {
    "day": "2022-06-13T04:00:00.000Z",
    "active_cases": 72545
  },
  {
    "day": "2022-06-20T04:00:00.000Z",
    "active_cases": 73143
  },
  {
    "day": "2022-06-27T04:00:00.000Z",
    "active_cases": 74147
  },
  {
    "day": "2022-07-04T04:00:00.000Z",
    "active_cases": 74865
  },
  {
    "day": "2022-07-11T04:00:00.000Z",
    "active_cases": 75670
  },
  {
    "day": "2022-07-18T04:00:00.000Z",
    "active_cases": 76700
  },
  {
    "day": "2022-07-25T04:00:00.000Z",
    "active_cases": 77422
  },
  {
    "day": "2022-08-01T04:00:00.000Z",
    "active_cases": 78185
  },
  {
    "day": "2022-08-08T04:00:00.000Z",
    "active_cases": 79001
  },
  {
    "day": "2022-08-15T04:00:00.000Z",
    "active_cases": 79635
  },
  {
    "day": "2022-08-22T04:00:00.000Z",
    "active_cases": 80165
  },
  {
    "day": "2022-08-29T04:00:00.000Z",
    "active_cases": 80914
  },
  {
    "day": "2022-09-05T04:00:00.000Z",
    "active_cases": 81608
  },
  {
    "day": "2022-09-12T04:00:00.000Z",
    "active_cases": 82365
  },
  {
    "day": "2022-09-19T04:00:00.000Z",
    "active_cases": 83186
  },
  {
    "day": "2022-09-26T04:00:00.000Z",
    "active_cases": 83863
  },
  {
    "day": "2022-10-03T04:00:00.000Z",
    "active_cases": 84591
  },
  {
    "day": "2022-10-10T04:00:00.000Z",
    "active_cases": 85369
  },
  {
    "day": "2022-10-17T04:00:00.000Z",
    "active_cases": 86064
  },
  {
    "day": "2022-10-24T04:00:00.000Z",
    "active_cases": 86751
  },
  {
    "day": "2022-10-31T04:00:00.000Z",
    "active_cases": 87574
  },
  {
    "day": "2022-11-07T05:00:00.000Z",
    "active_cases": 88357
  },
  {
    "day": "2022-11-14T05:00:00.000Z",
    "active_cases": 89036
  },
  {
    "day": "2022-11-21T05:00:00.000Z",
    "active_cases": 89567
  },
  {
    "day": "2022-11-28T05:00:00.000Z",
    "active_cases": 90399
  },
  {
    "day": "2022-12-05T05:00:00.000Z",
    "active_cases": 91176
  },
  {
    "day": "2022-12-12T05:00:00.000Z",
    "active_cases": 91944
  },
  {
    "day": "2022-12-19T05:00:00.000Z",
    "active_cases": 92786
  },
  {
    "day": "2022-12-26T05:00:00.000Z",
    "active_cases": 93457
  },
  {
    "day": "2023-01-02T05:00:00.000Z",
    "active_cases": 94101
  },
  {
    "day": "2023-01-09T05:00:00.000Z",
    "active_cases": 95258
  },
  {
    "day": "2023-01-16T05:00:00.000Z",
    "active_cases": 96077
  },
  {
    "day": "2023-01-23T05:00:00.000Z",
    "active_cases": 96926
  },
  {
    "day": "2023-01-30T05:00:00.000Z",
    "active_cases": 97686
  },
  {
    "day": "2023-02-06T05:00:00.000Z",
    "active_cases": 98453
  },
  {
    "day": "2023-02-13T05:00:00.000Z",
    "active_cases": 99171
  },
  {
    "day": "2023-02-20T05:00:00.000Z",
    "active_cases": 99897
  },
  {
    "day": "2023-02-27T05:00:00.000Z",
    "active_cases": 100789
  },
  {
    "day": "2023-03-06T05:00:00.000Z",
    "active_cases": 101803
  },
  {
    "day": "2023-03-13T04:00:00.000Z",
    "active_cases": 102764
  },
  {
    "day": "2023-03-20T04:00:00.000Z",
    "active_cases": 103708
  },
  {
    "day": "2023-03-27T04:00:00.000Z",
    "active_cases": 104582
  },
  {
    "day": "2023-04-03T04:00:00.000Z",
    "active_cases": 105374
  },
  {
    "day": "2023-04-10T04:00:00.000Z",
    "active_cases": 106387
  },
  {
    "day": "2023-04-17T04:00:00.000Z",
    "active_cases": 107458
  },
  {
    "day": "2023-04-24T04:00:00.000Z",
    "active_cases": 108580
  },
  {
    "day": "2023-05-01T04:00:00.000Z",
    "active_cases": 109905
  },
  {
    "day": "2023-05-08T04:00:00.000Z",
    "active_cases": 110853
  },
  {
    "day": "2023-05-15T04:00:00.000Z",
    "active_cases": 111840
  },
  {
    "day": "2023-05-22T04:00:00.000Z",
    "active_cases": 112911
  },
  {
    "day": "2023-05-29T04:00:00.000Z",
    "active_cases": 114009
  },
  {
    "day": "2023-06-05T04:00:00.000Z",
    "active_cases": 115309
  },
  {
    "day": "2023-06-12T04:00:00.000Z",
    "active_cases": 116459
  },
  {
    "day": "2023-06-19T04:00:00.000Z",
    "active_cases": 117619
  },
  {
    "day": "2023-06-26T04:00:00.000Z",
    "active_cases": 118942
  },
  {
    "day": "2023-07-03T04:00:00.000Z",
    "active_cases": 120131
  },
  {
    "day": "2023-07-10T04:00:00.000Z",
    "active_cases": 121751
  },
  {
    "day": "2023-07-17T04:00:00.000Z",
    "active_cases": 123089
  },
  {
    "day": "2023-07-24T04:00:00.000Z",
    "active_cases": 124464
  },
  {
    "day": "2023-07-31T04:00:00.000Z",
    "active_cases": 126275
  },
  {
    "day": "2023-08-07T04:00:00.000Z",
    "active_cases": 128022
  },
  {
    "day": "2023-08-14T04:00:00.000Z",
    "active_cases": 129968
  },
  {
    "day": "2023-08-21T04:00:00.000Z",
    "active_cases": 131482
  },
  {
    "day": "2023-08-28T04:00:00.000Z",
    "active_cases": 133408
  },
  {
    "day": "2023-09-04T04:00:00.000Z",
    "active_cases": 135296
  },
  {
    "day": "2023-09-11T04:00:00.000Z",
    "active_cases": 137406
  },
  {
    "day": "2023-09-18T04:00:00.000Z",
    "active_cases": 139451
  },
  {
    "day": "2023-09-25T04:00:00.000Z",
    "active_cases": 141448
  },
  {
    "day": "2023-10-02T04:00:00.000Z",
    "active_cases": 143610
  },
  {
    "day": "2023-10-09T04:00:00.000Z",
    "active_cases": 145736
  },
  {
    "day": "2023-10-16T04:00:00.000Z",
    "active_cases": 148241
  },
  {
    "day": "2023-10-23T04:00:00.000Z",
    "active_cases": 150322
  },
  {
    "day": "2023-10-30T04:00:00.000Z",
    "active_cases": 152459
  },
  {
    "day": "2023-11-06T05:00:00.000Z",
    "active_cases": 154897
  },
  {
    "day": "2023-11-13T05:00:00.000Z",
    "active_cases": 157287
  },
  {
    "day": "2023-11-20T05:00:00.000Z",
    "active_cases": 158630
  },
  {
    "day": "2023-11-27T05:00:00.000Z",
    "active_cases": 161114
  },
  {
    "day": "2023-12-04T05:00:00.000Z",
    "active_cases": 163821
  },
  {
    "day": "2023-12-11T05:00:00.000Z",
    "active_cases": 166375
  },
  {
    "day": "2023-12-18T05:00:00.000Z",
    "active_cases": 168540
  },
  {
    "day": "2023-12-25T05:00:00.000Z",
    "active_cases": 170294
  },
  {
    "day": "2024-01-01T05:00:00.000Z",
    "active_cases": 172341
  },
  {
    "day": "2024-01-08T05:00:00.000Z",
    "active_cases": 174735
  },
  {
    "day": "2024-01-15T05:00:00.000Z",
    "active_cases": 175464
  }
]