[
  {
    "count": 165,
    "category": "Outside NYC.Issued Pandemic.All.Holdover"
  },
  {
    "count": 87,
    "category": "Outside NYC.Issued Prepandemic.All.Holdover"
  },
  {
    "count": 634,
    "category": "NYC.Issued Pandemic.Commercial.Holdover"
  },
  {
    "count": 561,
    "category": "NYC.Issued Prepandemic.Commercial.Holdover"
  },
  {
    "count": 108,
    "category": "Outside NYC.Issued Pandemic.Commercial.Holdover"
  },
  {
    "count": 15510,
    "category": "NYC.Issued Pandemic.Residential.Holdover"
  },
  {
    "count": 7085,
    "category": "NYC.Issued Prepandemic.Residential.Holdover"
  },
  {
    "count": 2247,
    "category": "Outside NYC.Issued Pandemic.Residential.Holdover"
  },
  {
    "count": 651,
    "category": "Outside NYC.Issued Pandemic.All.Non-Payment"
  },
  {
    "count": 417,
    "category": "Outside NYC.Issued Prepandemic.All.Non-Payment"
  },
  {
    "count": 4029,
    "category": "NYC.Issued Pandemic.Commercial.Non-Payment"
  },
  {
    "count": 7388,
    "category": "NYC.Issued Prepandemic.Commercial.Non-Payment"
  },
  {
    "count": 201,
    "category": "Outside NYC.Issued Pandemic.Commercial.Non-Payment"
  },
  {
    "count": 95421,
    "category": "NYC.Issued Pandemic.Residential.Non-Payment"
  },
  {
    "count": 127685,
    "category": "NYC.Issued Prepandemic.Residential.Non-Payment"
  },
  {
    "count": 9890,
    "category": "Outside NYC.Issued Pandemic.Residential.Non-Payment"
  },
  {
    "count": 2,
    "category": "Outside NYC.Issued Prepandemic.Residential.Non-Payment"
  }
]