[
  {
    "count": 70,
    "category": "Outside NYC.Issued Pandemic.All.Holdover"
  },
  {
    "count": 45,
    "category": "Outside NYC.Issued Prepandemic.All.Holdover"
  },
  {
    "count": 812,
    "category": "NYC.Issued Pandemic.Commercial.Holdover"
  },
  {
    "count": 193,
    "category": "NYC.Issued Prepandemic.Commercial.Holdover"
  },
  {
    "count": 57,
    "category": "Outside NYC.Issued Pandemic.Commercial.Holdover"
  },
  {
    "count": 20183,
    "category": "NYC.Issued Pandemic.Residential.Holdover"
  },
  {
    "count": 1960,
    "category": "NYC.Issued Prepandemic.Residential.Holdover"
  },
  {
    "count": 1393,
    "category": "Outside NYC.Issued Pandemic.Residential.Holdover"
  },
  {
    "count": 239,
    "category": "Outside NYC.Issued Pandemic.All.Non-Payment"
  },
  {
    "count": 303,
    "category": "Outside NYC.Issued Prepandemic.All.Non-Payment"
  },
  {
    "count": 4718,
    "category": "NYC.Issued Pandemic.Commercial.Non-Payment"
  },
  {
    "count": 416,
    "category": "NYC.Issued Prepandemic.Commercial.Non-Payment"
  },
  {
    "count": 126,
    "category": "Outside NYC.Issued Pandemic.Commercial.Non-Payment"
  },
  {
    "count": 111324,
    "category": "NYC.Issued Pandemic.Residential.Non-Payment"
  },
  {
    "count": 14182,
    "category": "NYC.Issued Prepandemic.Residential.Non-Payment"
  },
  {
    "count": 4666,
    "category": "Outside NYC.Issued Pandemic.Residential.Non-Payment"
  }
]